Workbook

Sheet Ordre d'exécution
A1: Backlog GestionProjet — ordre d'exécution
A2: Généré le 16/10/2026 14:45 depuis backlog/BACKLOG.md. Ne pas modifier : les statuts changent via /lancer-phase, /valider-phase, /refuser-tache et scripts/backlog.py.
A4: Phase | B4: Titre | C4: Statut phase | D4: Modèle conseillé | E4: Tâches | F4: Faites | G4: Avancement | H4: Bloquées
A5: P0 | B5: Initialisation et outillage | C5: VALIDEE | D5: sonnet | E5: =COUNTA('P0'!B8:B200) | F5: =COUNTIF('P0'!F8:F200,"A_VALIDER")+COUNTIF('P0'!F8:F200,"VALIDE") | G5: =IF(E5=0,0,F5/E5) | H5: =COUNTIF('P0'!F8:F200,"BLOQUE")
A6: P1 | B6: Socle backend .NET 10 | C6: EN_COURS | D6: opus | E6: =COUNTA('P1'!B8:B200) | F6: =COUNTIF('P1'!F8:F200,"A_VALIDER")+COUNTIF('P1'!F8:F200,"VALIDE") | G6: =IF(E6=0,0,F6/E6) | H6: =COUNTIF('P1'!F8:F200,"BLOQUE")
A7: P2 | B7: Socle frontend Blazor WebAssembly et BFF | C7: NON_DEMARREE | D7: sonnet | E7: =COUNTA('P2'!B8:B200) | F7: =COUNTIF('P2'!F8:F200,"A_VALIDER")+COUNTIF('P2'!F8:F200,"VALIDE") | G7: =IF(E7=0,0,F7/E7) | H7: =COUNTIF('P2'!F8:F200,"BLOQUE")
A8: P3 | B8: Conteneurisation et intégration continue GitHub Actions | C8: NON_DEMARREE | D8: sonnet | E8: =COUNTA('P3'!B8:B200) | F8: =COUNTIF('P3'!F8:F200,"A_VALIDER")+COUNTIF('P3'!F8:F200,"VALIDE") | G8: =IF(E8=0,0,F8/E8) | H8: =COUNTIF('P3'!F8:F200,"BLOQUE")
A9: P4 | B9: Module Organisation et périmètre hiérarchique | C9: NON_DEMARREE | D9: sonnet | E9: =COUNTA('P4'!B8:B200) | F9: =COUNTIF('P4'!F8:F200,"A_VALIDER")+COUNTIF('P4'!F8:F200,"VALIDE") | G9: =IF(E9=0,0,F9/E9) | H9: =COUNTIF('P4'!F8:F200,"BLOQUE")
A10: P5 | B10: Projets et affectation en cascade | C10: NON_DEMARREE | D10: opus | E10: =COUNTA('P5'!B8:B200) | F10: =COUNTIF('P5'!F8:F200,"A_VALIDER")+COUNTIF('P5'!F8:F200,"VALIDE") | G10: =IF(E10=0,0,F10/E10) | H10: =COUNTIF('P5'!F8:F200,"BLOQUE")
A11: P6 | B11: Planification et ordonnancement | C11: NON_DEMARREE | D11: opus | E11: =COUNTA('P6'!B8:B200) | F11: =COUNTIF('P6'!F8:F200,"A_VALIDER")+COUNTIF('P6'!F8:F200,"VALIDE") | G11: =IF(E11=0,0,F11/E11) | H11: =COUNTIF('P6'!F8:F200,"BLOQUE")
A12: P7 | B12: Coût en temps | C12: NON_DEMARREE | D12: sonnet | E12: =COUNTA('P7'!B8:B200) | F12: =COUNTIF('P7'!F8:F200,"A_VALIDER")+COUNTIF('P7'!F8:F200,"VALIDE") | G12: =IF(E12=0,0,F12/E12) | H12: =COUNTIF('P7'!F8:F200,"BLOQUE")
A13: P8 | B13: Reporting par niveau hiérarchique | C13: NON_DEMARREE | D13: sonnet | E13: =COUNTA('P8'!B8:B200) | F13: =COUNTIF('P8'!F8:F200,"A_VALIDER")+COUNTIF('P8'!F8:F200,"VALIDE") | G13: =IF(E13=0,0,F13/E13) | H13: =COUNTIF('P8'!F8:F200,"BLOQUE")
A14: P9 | B14: Collaboration et services transverses | C14: NON_DEMARREE | D14: sonnet | E14: =COUNTA('P9'!B8:B200) | F14: =COUNTIF('P9'!F8:F200,"A_VALIDER")+COUNTIF('P9'!F8:F200,"VALIDE") | G14: =IF(E14=0,0,F14/E14) | H14: =COUNTIF('P9'!F8:F200,"BLOQUE")
A15: P10 | B15: Modélisation et diagrammes | C15: NON_DEMARREE | D15: opus | E15: =COUNTA('P10'!B8:B200) | F15: =COUNTIF('P10'!F8:F200,"A_VALIDER")+COUNTIF('P10'!F8:F200,"VALIDE") | G15: =IF(E15=0,0,F15/E15) | H15: =COUNTIF('P10'!F8:F200,"BLOQUE")
A16: P11 | B16: Générateur de code | C16: NON_DEMARREE | D16: opus | E16: =COUNTA('P11'!B8:B200) | F16: =COUNTIF('P11'!F8:F200,"A_VALIDER")+COUNTIF('P11'!F8:F200,"VALIDE") | G16: =IF(E16=0,0,F16/E16) | H16: =COUNTIF('P11'!F8:F200,"BLOQUE")
A17: P12 | B17: Intégration GitLab | C17: NON_DEMARREE | D17: sonnet | E17: =COUNTA('P12'!B8:B200) | F17: =COUNTIF('P12'!F8:F200,"A_VALIDER")+COUNTIF('P12'!F8:F200,"VALIDE") | G17: =IF(E17=0,0,F17/E17) | H17: =COUNTIF('P12'!F8:F200,"BLOQUE")
A18: P13 | B18: Déploiement Docker | C18: NON_DEMARREE | D18: sonnet | E18: =COUNTA('P13'!B8:B200) | F18: =COUNTIF('P13'!F8:F200,"A_VALIDER")+COUNTIF('P13'!F8:F200,"VALIDE") | G18: =IF(E18=0,0,F18/E18) | H18: =COUNTIF('P13'!F8:F200,"BLOQUE")
A19: P14 | B19: Cadrage, exigences et conception des écrans | C19: NON_DEMARREE | D19: sonnet | E19: =COUNTA('P14'!B8:B200) | F19: =COUNTIF('P14'!F8:F200,"A_VALIDER")+COUNTIF('P14'!F8:F200,"VALIDE") | G19: =IF(E19=0,0,F19/E19) | H19: =COUNTIF('P14'!F8:F200,"BLOQUE")
A20: P15 | B20: Qualité, recette et DevSecOps | C20: NON_DEMARREE | D20: sonnet | E20: =COUNTA('P15'!B8:B200) | F20: =COUNTIF('P15'!F8:F200,"A_VALIDER")+COUNTIF('P15'!F8:F200,"VALIDE") | G20: =IF(E20=0,0,F20/E20) | H20: =COUNTIF('P15'!F8:F200,"BLOQUE")
A21: P16 | B21: Documentation, méthodes agiles, automatisation et API | C21: NON_DEMARREE | D21: sonnet | E21: =COUNTA('P16'!B8:B200) | F21: =COUNTIF('P16'!F8:F200,"A_VALIDER")+COUNTIF('P16'!F8:F200,"VALIDE") | G21: =IF(E21=0,0,F21/E21) | H21: =COUNTIF('P16'!F8:F200,"BLOQUE")
A22: P17 | B22: Expérience utilisateur transverse et accessibilité | C22: NON_DEMARREE | D22: sonnet | E22: =COUNTA('P17'!B8:B200) | F22: =COUNTIF('P17'!F8:F200,"A_VALIDER")+COUNTIF('P17'!F8:F200,"VALIDE") | G22: =IF(E22=0,0,F22/E22) | H22: =COUNTIF('P17'!F8:F200,"BLOQUE")
A23: P18 | B23: Sécurité Keycloak et durcissement | C23: NON_DEMARREE | D23: opus | E23: =COUNTA('P18'!B8:B200) | F23: =COUNTIF('P18'!F8:F200,"A_VALIDER")+COUNTIF('P18'!F8:F200,"VALIDE") | G23: =IF(E23=0,0,F23/E23) | H23: =COUNTIF('P18'!F8:F200,"BLOQUE")
A24: P19 | B24: Performance, recette finale et mise en production | C24: NON_DEMARREE | D24: sonnet | E24: =COUNTA('P19'!B8:B200) | F24: =COUNTIF('P19'!F8:F200,"A_VALIDER")+COUNTIF('P19'!F8:F200,"VALIDE") | G24: =IF(E24=0,0,F24/E24) | H24: =COUNTIF('P19'!F8:F200,"BLOQUE")
B25: Total | E25: =SUM(E5:E24) | F25: =SUM(F5:F24) | G25: =IF(E25=0,0,F25/E25) | H25: =SUM(H5:H24)
A27: Séquence d'exécution des tâches
A28: N° | B28: Phase | C28: Code | D28: Tâche | E28: Modèle | F28: Ordre | G28: Dépend de | H28: Statut | I28: Hypothèses
A29: 1 | B29: P0 · Initialisation et outillage | C29: P0-T01 | D29: Initialiser le dépôt Git et la branche de phase | E29: haiku | F29: 1 | G29: — | H29: VALIDE
A30: 2 | B30: P0 · Initialisation et outillage | C30: P0-T02 | D30: Script de vérification de l'environnement | E30: haiku | F30: 2 | G30: P0-T01 | H30: VALIDE | I30: H-015
A31: 3 | B31: P0 · Initialisation et outillage | C31: P0-T03 | D31: Valider l'instance PostgreSQL de test et le schéma de référence | E31: sonnet | F31: 3 | G31: P0-T01 | H31: VALIDE | I31: H-016
A32: 4 | B32: P0 · Initialisation et outillage | C32: P0-T04 | D32: Conventions de build .NET centralisées | E32: haiku | F32: 4 | G32: P0-T01 | H32: VALIDE | I32: H-017
A33: 5 | B33: P0 · Initialisation et outillage | C33: P0-T05 | D33: Modèles GitLab et guide de contribution | E33: haiku | F33: 5 | G33: P0-T01 | H33: VALIDE
A34: 6 | B34: P0 · Initialisation et outillage | C34: P0-T06 | D34: Rapport d'outillage Claude Code | E34: haiku | F34: 6 | G34: P0-T02 | H34: VALIDE | I34: H-003, H-018
A35: 7 | B35: P1 · Socle backend .NET 10 | C35: P1-T01 | D35: Créer la solution et le projet Gprojet-Backend | E35: sonnet | F35: 1 | G35: — | H35: A_VALIDER
A36: 8 | B36: P1 · Socle backend .NET 10 | C36: P1-T02 | D36: Tests d'architecture par espace de noms | E36: opus | F36: 2 | G36: P1-T01 | H36: A_VALIDER | I36: H-019
A37: 9 | B37: P1 · Socle backend .NET 10 | C37: P1-T03 | D37: Common : primitives transverses | E37: sonnet | F37: 3 | G37: P1-T01 | H37: A_VALIDER | I37: H-020
A38: 10 | B38: P1 · Socle backend .NET 10 | C38: P1-T04 | D38: Entités du domaine (6 schémas) | E38: opus | F38: 4 | G38: P1-T03 | H38: A_VALIDER | I38: H-021
A39: 11 | B39: P1 · Socle backend .NET 10 | C39: P1-T05 | D39: DbContext et configurations EF Core | E39: opus | F39: 5 | G39: P1-T04 | H39: A_VALIDER | I39: H-022
A40: 12 | B40: P1 · Socle backend .NET 10 | C40: P1-T06 | D40: Migration initiale identique au schéma de référence | E40: opus | F40: 6 | G40: P1-T05 | H40: EN_COURS | I40: H-023
A41: 13 | B41: P1 · Socle backend .NET 10 | C41: P1-T07 | D41: Intercepteurs : audit, suppression logique, historique chaîné | E41: sonnet | F41: 7 | G41: P1-T06 | H41: NON_FAIT
A42: 14 | B42: P1 · Socle backend .NET 10 | C42: P1-T08 | D42: Unit of Work et repositories de base | E42: sonnet | F42: 8 | G42: P1-T06 | H42: NON_FAIT
A43: 15 | B43: P1 · Socle backend .NET 10 | C43: P1-T09 | D43: Socle API : DI, erreurs, OpenAPI, logs, santé | E43: sonnet | F43: 9 | G43: P1-T08 | H43: NON_FAIT | I43: H-004
A44: 16 | B44: P1 · Socle backend .NET 10 | C44: P1-T10 | D44: Authentification de développement et utilisateur courant | E44: sonnet | F44: 10 | G44: P1-T09 | H44: NON_FAIT
A45: 17 | B45: P1 · Socle backend .NET 10 | C45: P1-T11 | D45: Données de démonstration | E45: haiku | F45: 11 | G45: P1-T06 | H45: NON_FAIT
A46: 18 | B46: P2 · Socle frontend Blazor WebAssembly et BFF | C46: P2-T01 | D46: Projet Gprojet-Front, hébergement par le backend et tests bUnit | E46: sonnet | F46: 1 | G46: — | H46: NON_FAIT
A47: 19 | B47: P2 · Socle frontend Blazor WebAssembly et BFF | C47: P2-T02 | D47: Charte HCP : intégration de app.css et des ressources | E47: sonnet | F47: 2 | G47: P2-T01 | H47: NON_FAIT | I47: H-014
A48: 20 | B48: P2 · Socle frontend Blazor WebAssembly et BFF | C48: P2-T03 | D48: Layout principal et navigation par rôle | E48: sonnet | F48: 3 | G48: P2-T02 | H48: NON_FAIT
A49: 21 | B49: P2 · Socle frontend Blazor WebAssembly et BFF | C49: P2-T04 | D49: Mouvement selon la charte (motion-design) | E49: sonnet | F49: 4 | G49: P2-T02 | H49: NON_FAIT
A50: 22 | B50: P2 · Socle frontend Blazor WebAssembly et BFF | C50: P2-T05 | D50: Couche Api : clients HTTP typés | E50: sonnet | F50: 5 | G50: P2-T01 | H50: NON_FAIT
A51: 23 | B51: P2 · Socle frontend Blazor WebAssembly et BFF | C51: P2-T06 | D51: Authentification côté front (BFF, mode dev) | E51: sonnet | F51: 6 | G51: P2-T05 | H51: NON_FAIT
A52: 24 | B52: P2 · Socle frontend Blazor WebAssembly et BFF | C52: P2-T07 | D52: État partagé et services front de base | E52: sonnet | F52: 7 | G52: P2-T06 | H52: NON_FAIT
A53: 25 | B53: P2 · Socle frontend Blazor WebAssembly et BFF | C53: P2-T08 | D53: Internationalisation fr / en / ar (RTL) | E53: sonnet | F53: 8 | G53: P2-T03 | H53: NON_FAIT
A54: 26 | B54: P2 · Socle frontend Blazor WebAssembly et BFF | C54: P2-T09 | D54: Pages système | E54: haiku | F54: 9 | G54: P2-T08 | H54: NON_FAIT
A55: 27 | B55: P3 · Conteneurisation et intégration continue GitHub Actions | C55: P3-T01 | D55: Dockerfile de l'application | E55: sonnet | F55: 1 | G55: — | H55: NON_FAIT | I55: H-001
A56: 28 | B56: P3 · Conteneurisation et intégration continue GitHub Actions | C56: P3-T02 | D56: docker compose de développement | E56: sonnet | F56: 2 | G56: P3-T01 | H56: NON_FAIT
A57: 29 | B57: P3 · Conteneurisation et intégration continue GitHub Actions | C57: P3-T03 | D57: Tests en CI avec PostgreSQL de service | E57: sonnet | F57: 3 | G57: — | H57: NON_FAIT
A58: 30 | B58: P3 · Conteneurisation et intégration continue GitHub Actions | C58: P3-T04 | D58: Workflow GitHub Actions | E58: sonnet | F58: 4 | G58: P3-T01, P3-T03 | H58: NON_FAIT | I58: H-002
A59: 31 | B59: P3 · Conteneurisation et intégration continue GitHub Actions | C59: P3-T05 | D59: Documentation de déploiement local | E59: haiku | F59: 5 | G59: P3-T02, P3-T04 | H59: NON_FAIT
A60: 32 | B60: P4 · Module Organisation et périmètre hiérarchique | C60: P4-T01 | D60: Service de périmètre et rôles déduits | E60: opus | F60: 1 | G60: — | H60: NON_FAIT
A61: 33 | B61: P4 · Module Organisation et périmètre hiérarchique | C61: P4-T02 | D61: Organigramme : API | E61: sonnet | F61: 2 | G61: P4-T01 | H61: NON_FAIT
A62: 34 | B62: P4 · Module Organisation et périmètre hiérarchique | C62: P4-T03 | D62: Agents, rattachements et compétences : API | E62: sonnet | F62: 3 | G62: P4-T02 | H62: NON_FAIT
A63: 35 | B63: P4 · Module Organisation et périmètre hiérarchique | C63: P4-T04 | D63: Délégations, absences et calendrier : API | E63: sonnet | F63: 4 | G63: P4-T01 | H63: NON_FAIT
A64: 36 | B64: P4 · Module Organisation et périmètre hiérarchique | C64: P4-T05 | D64: Pages organigramme | E64: sonnet | F64: 5 | G64: P4-T02 | H64: NON_FAIT
A65: 37 | B65: P4 · Module Organisation et périmètre hiérarchique | C65: P4-T06 | D65: Pages agents | E65: sonnet | F65: 6 | G65: P4-T03 | H65: NON_FAIT
A66: 38 | B66: P4 · Module Organisation et périmètre hiérarchique | C66: P4-T07 | D66: Pages délégations, absences et calendrier | E66: sonnet | F66: 7 | G66: P4-T04 | H66: NON_FAIT
A67: 39 | B67: P4 · Module Organisation et périmètre hiérarchique | C67: P4-T08 | D67: Documentation fonctionnelle du module | E67: haiku | F67: 8 | G67: P4-T05, P4-T06, P4-T07 | H67: NON_FAIT
A68: 40 | B68: P5 · Projets et affectation en cascade | C68: P5-T01 | D68: Référentiels : types de projet et modèles de phases | E68: sonnet | F68: 1 | G68: — | H68: NON_FAIT
A69: 41 | B69: P5 · Projets et affectation en cascade | C69: P5-T02 | D69: Création de projet | E69: opus | F69: 2 | G69: P5-T01 | H69: NON_FAIT
A70: 42 | B70: P5 · Projets et affectation en cascade | C70: P5-T03 | D70: Affectation en cascade | E70: opus | F70: 3 | G70: P5-T02 | H70: NON_FAIT
... A87: 59 | B87: P6 · Planification et ordonnancement | C87: P6-T10 | D87: Pages liste, Kanban et fiches | E87: sonnet | F87: 10 | G87: P6-T08 | H87: NON_FAIT
A88: 60 | B88: P6 · Planification et ordonnancement | C88: P6-T11 | D88: Gantt et réseau PERT | E88: opus | F88: 11 | G88: P6-T06, P6-T10 | H88: NON_FAIT | I88: H-005
A89: 61 | B89: P6 · Planification et ordonnancement | C89: P6-T12 | D89: Documentation du module | E89: haiku | F89: 12 | G89: P6-T11 | H89: NON_FAIT
A90: 62 | B90: P7 · Coût en temps | C90: P7-T01 | D90: Référentiels et paramètres du temps | E90: haiku | F90: 1 | G90: — | H90: NON_FAIT
A91: 63 | B91: P7 · Coût en temps | C91: P7-T02 | D91: Feuilles de temps et saisies | E91: sonnet | F91: 2 | G91: P7-T01 | H91: NON_FAIT
A92: 64 | B92: P7 · Coût en temps | C92: P7-T03 | D92: Chronomètre | E92: sonnet | F92: 3 | G92: P7-T02 | H92: NON_FAIT
A93: 65 | B93: P7 · Coût en temps | C93: P7-T04 | D93: Circuit de validation des temps | E93: opus | F93: 4 | G93: P7-T02 | H93: NON_FAIT
A94: 66 | B94: P7 · Coût en temps | C94: P7-T05 | D94: Prévu, consommé, reste à faire et alertes | E94: sonnet | F94: 5 | G94: P7-T04 | H94: NON_FAIT
A95: 67 | B95: P7 · Coût en temps | C95: P7-T06 | D95: Plan de charge et taux d'occupation | E95: sonnet | F95: 6 | G95: P7-T05 | H95: NON_FAIT
A96: 68 | B96: P7 · Coût en temps | C96: P7-T07 | D96: Pages saisie, chronomètre et validation | E96: sonnet | F96: 7 | G96: P7-T04 | H96: NON_FAIT
A97: 69 | B97: P7 · Coût en temps | C97: P7-T08 | D97: Page plan de charge | E97: sonnet | F97: 8 | G97: P7-T06 | H97: NON_FAIT
A98: 70 | B98: P8 · Reporting par niveau hiérarchique | C98: P8-T01 | D98: Requêtes de reporting | E98: opus | F98: 1 | G98: — | H98: NON_FAIT
A99: 71 | B99: P8 · Reporting par niveau hiérarchique | C99: P8-T02 | D99: Tableau de bord Directeur | E99: sonnet | F99: 2 | G99: P8-T01 | H99: NON_FAIT
A100: 72 | B100: P8 · Reporting par niveau hiérarchique | C100: P8-T03 | D100: Tableau de bord Chef de division | E100: sonnet | F100: 3 | G100: P8-T01 | H100: NON_FAIT
... A103: 75 | B103: P8 · Reporting par niveau hiérarchique | C103: P8-T06 | D103: Navigation de drill-down | E103: sonnet | F103: 6 | G103: P8-T02, P8-T03, P8-T04 | H103: NON_FAIT
A104: 76 | B104: P8 · Reporting par niveau hiérarchique | C104: P8-T07 | D104: Exports Excel et PDF | E104: sonnet | F104: 7 | G104: P8-T01 | H104: NON_FAIT | I104: H-006, H-007
A105: 77 | B105: P8 · Reporting par niveau hiérarchique | C105: P8-T08 | D105: Rapports planifiés par e-mail | E105: sonnet | F105: 8 | G105: P8-T07 | H105: NON_FAIT
A106: 78 | B106: P9 · Collaboration et services transverses | C106: P9-T01 | D106: Commentaires et mentions | E106: sonnet | F106: 1 | G106: — | H106: NON_FAIT
A107: 79 | B107: P9 · Collaboration et services transverses | C107: P9-T02 | D107: Pièces jointes | E107: sonnet | F107: 2 | G107: — | H107: NON_FAIT | I107: H-008
A108: 80 | B108: P9 · Collaboration et services transverses | C108: P9-T03 | D108: Notifications temps réel | E108: sonnet | F108: 3 | G108: P9-T01 | H108: NON_FAIT
A109: 81 | B109: P9 · Collaboration et services transverses | C109: P9-T04 | D109: Abonnements (observateurs) | E109: sonnet | F109: 4 | G109: P9-T03 | H109: NON_FAIT
A110: 82 | B110: P9 · Collaboration et services transverses | C110: P9-T05 | D110: Historique et vérification d'intégrité | E110: sonnet | F110: 5 | G110: — | H110: NON_FAIT
A111: 83 | B111: P10 · Modélisation et diagrammes | C111: P10-T01 | D111: API du métamodèle | E111: sonnet | F111: 1 | G111: — | H111: NON_FAIT
A112: 84 | B112: P10 · Modélisation et diagrammes | C112: P10-T02 | D112: Contrôle de cohérence d'un modèle | E112: opus | F112: 2 | G112: P10-T01 | H112: NON_FAIT
A113: 85 | B113: P10 · Modélisation et diagrammes | C113: P10-T03 | D113: Transformation MCD → MLD (règles R1 à R10) | E113: opus | F113: 3 | G113: P10-T02 | H113: NON_FAIT
A114: 86 | B114: P10 · Modélisation et diagrammes | C114: P10-T04 | D114: Génération SQL (MPD) PostgreSQL | E114: opus | F114: 4 | G114: P10-T03 | H114: NON_FAIT
A115: 87 | B115: P10 · Modélisation et diagrammes | C115: P10-T05 | D115: Import / export et rétro-ingénierie | E115: opus | F115: 5 | G115: P10-T04 | H115: NON_FAIT
A116: 88 | B116: P10 · Modélisation et diagrammes | C116: P10-T06 | D116: Dogfooding : la plateforme se décrit elle-même | E116: opus | F116: 6 | G116: P10-T05 | H116: NON_FAIT
A117: 89 | B117: P10 · Modélisation et diagrammes | C117: P10-T07 | D117: Éditeur visuel MCD / classes | E117: opus | F117: 7 | G117: P10-T01 | H117: NON_FAIT | I117: H-009
A118: 90 | B118: P10 · Modélisation et diagrammes | C118: P10-T08 | D118: Diagrammes documentaires | E118: sonnet | F118: 8 | G118: P10-T01 | H118: NON_FAIT | I118: H-010
A119: 91 | B119: P10 · Modélisation et diagrammes | C119: P10-T09 | D119: Versions, comparaison, validation et exports | E119: sonnet | F119: 9 | G119: P10-T07, P10-T08 | H119: NON_FAIT
A120: 92 | B120: P11 · Générateur de code | C120: P11-T01 | D120: Moteur de génération Scriban | E120: opus | F120: 1 | G120: — | H120: NON_FAIT
...

Sheet P0
A1: P0 · Initialisation et outillage
A2: Objectif : dépôt Git propre, conventions, environnement vérifié, base de test opérationnelle. Livrable : un dépôt prêt à recevoir la solution .NET.
A3: Statut phase | B3: VALIDEE
A4: Modèle conseillé | B4: sonnet
A5: Avancement | B5: =IF(COUNTA(B8:B200)=0,0,(COUNTIF(F8:F200,"A_VALIDER")+COUNTIF(F8:F200,"VALIDE"))/COUNTA(B8:B200))
A6: ← Retour à l'ordre d'exécution
A7: Ordre | B7: Code | C7: Tâche | D7: Modèle | E7: Dépend de | F7: Statut | G7: Explication | H7: Test de validation | I7: Retours utilisateur | J7: Hypothèses liées
A8: 1 | B8: P0-T01 | C8: Initialiser le dépôt Git et la branche de phase | D8: haiku | E8: — | F8: VALIDE | G8: git init -b main à la racine du projet, premier commit contenant l'existant (CLAUDE.md, .claude/, backlog/, scripts/, database/), puis branche phase/P0-initialisation. Le .gitignore existe déjà (secrets locaux dont .claude/settings.local.json, .pgtest/, .NET) : le vérifier avant le premier git add, le compléter si besoin. Créer .gitattributes (* text=auto eol=lf, *.sql et *.md en LF, *.ps1 en CRLF). | H8: git log --oneline montre au moins 2 commits ; git status --porcelain est vide ; git check-ignore .pgtest/x bin/x .claude/settings.local.json renvoie les trois chemins ; git ls-files | grep -c settings.local renvoie 0.
A9: 2 | B9: P0-T02 | C9: Script de vérification de l'environnement | D9: haiku | E9: P0-T01 | F9: VALIDE | G9: scripts/verifier-env.py affiche un tableau OK / MANQUANT / OPTIONNEL pour : .NET SDK 10, Python ≥ 3.12 avec le module openpyxl (export Excel du backlog), binaires PostgreSQL 18 (PG_BIN), Git, Node.js (optionnel : ponytail, motion), Docker (requis à partir de P3), uv et graphify (optionnels). Code de sortie 1 si un outil requis manque. | H9: python scripts/verifier-env.py affiche le tableau et sort en 0 sur ce poste (dotnet, python, PostgreSQL, git présents) ; en masquant PG_BIN vers un dossier vide, il sort en 1. | J9: H-015 (OUVERTE)
A10: 3 | B10: P0-T03 | C10: Valider l'instance PostgreSQL de test et le schéma de référence | D10: sonnet | E10: P0-T01 | F10: VALIDE | G10: utiliser scripts/pg-test.py pour démarrer l'instance jetable, appliquer database/01 et 02, exécuter database/03-tests-integrite.sql, puis arrêter. Ajouter scripts/tester-schema.py qui automatise cela et vérifie que les 13 blocs « attendu ERREUR » échouent et que les autres réussissent (analyse de la sortie psql). | H10: python scripts/tester-schema.py sort en 0 et affiche « 18/18 vérifications conformes » ; .pgtest/ n'existe plus après exécution. | J10: H-016 (OUVERTE)
A11: 4 | B11: P0-T04 | C11: Conventions de build .NET centralisées | D11: haiku | E11: P0-T01 | F11: VALIDE | G11: global.json (SDK 10.0.4xx, rollForward: latestFeature), Directory.Build.props (net10.0, Nullable enable, ImplicitUsings enable, TreatWarningsAsErrors true, AnalysisLevel latest-recommended, InvariantGlobalization false), Directory.Packages.props (gestion centralisée des versions : EF Core 10, Npgsql 10, Mapperly, FluentValidation, Serilog, xUnit, FluentAssertions, bUnit, NetArchTest, Microsoft.AspNetCore.Components.WebAssembly et .Server), .editorconfig (style C# : file-scoped namespaces, var si évident, accolades, nommage _champ). | H11: dotnet --version (dans le dossier) renvoie une version 10.0.4xx ; dotnet new console -o .tmpcheck && dotnet build .tmpcheck réussit avec les props appliquées (vérifier TreatWarningsAsErrors dans obj/*.nuget.g.props ou via dotnet msbuild -getProperty:TreatWarningsAsErrors) ; supprimer .tmpcheck. | J11: H-017 (REPONDUE)
A12: 5 | B12: P0-T05 | C12: Modèles GitLab et guide de contribution | D12: haiku | E12: P0-T01 | F12: VALIDE | G12: .gitlab/merge_request_templates/Phase.md (résumé de phase, tâches, preuves, hypothèses, checklist de revue), .gitlab/issue_templates/Anomalie.md et Demande.md, CONTRIBUTING.md (branches phase/Pn-…, commits Pn-Tnn: …, revue, règles des couches, comment lancer les tests). | H12: les 4 fichiers existent ; CONTRIBUTING.md contient les sections « Branches », « Commits », « Architecture », « Tests » (grep -c "^## " ≥ 4).
A13: 6 | B13: P0-T06 | C13: Rapport d'outillage Claude Code | D13: haiku | E13: P0-T02 | F13: VALIDE | G13: docs/OUTILLAGE.md : état réel des plugins / skills (graphify, ponytail, ui-ux-pro-max, motion-design) détecté sur le poste (~/.claude/skills, .claude/skills, ~/.claude/plugins), des hooks et des sous-agents du projet, avec la commande d'installation de chaque élément manquant (voir scripts/installer-outils.ps1). Si un outil manque, créer une hypothèse non bloquante. | H13: docs/OUTILLAGE.md liste les 4 outils avec un statut chacun ; python scripts/backlog.py contexte s'exécute sans erreur. | J13: H-003 (REPONDUE) H-018 (OUVERTE)

Sheet P1
A1: P1 · Socle backend .NET 10
A2: Objectif : solution en couches compilable, persistance PostgreSQL identique au schéma de référence, API démarrable. Livrable : Gprojet.slnx avec le projet unique Gprojet-Backend + API /health + tests d'architecture verts.
A3: Statut phase | B3: EN_COURS
A4: Modèle conseillé | B4: opus
A5: Avancement | B5: =IF(COUNTA(B8:B200)=0,0,(COUNTIF(F8:F200,"A_VALIDER")+COUNTIF(F8:F200,"VALIDE"))/COUNTA(B8:B200))
A6: ← Retour à l'ordre d'exécution
A7: Ordre | B7: Code | C7: Tâche | D7: Modèle | E7: Dépend de | F7: Statut | G7: Explication | H7: Test de validation | I7: Retours utilisateur | J7: Hypothèses liées
A8: 1 | B8: P1-T01 | C8: Créer la solution et le projet Gprojet-Backend | D8: sonnet | E8: — | F8: A_VALIDER | G8: Gprojet.slnx ; un seul projet backend src/Gprojet-Backend/Gprojet-Backend.csproj (Microsoft.NET.Sdk.Web, RootNamespace Gprojet.Backend) avec les dossiers-couches Web/, Orchestration/, Services/, Mapping/, Repositories/, Entities/, Contracts/, Infrastructure/, Common/ (espaces de noms alignés sur les dossiers) ; projet de tests tests/Gprojet-Backend.Tests (xUnit) avec Unitaires/, Integration/, Architecture/. Aucun autre projet (le front arrive en P2-T01). Demandes utilisateur à intégrer dans cette tâche : Directory.Packages.props → FluentAssertions en dernière 7.x stable (licence Apache 2.0, H-017) au lieu de 8.x ; migrer .gitlab/ vers .github/ (pull_request_template.md, ISSUE_TEMPLATE/Anomalie.md et Demande.md) et adapter CONTRIBUTING.md (pull requests GitHub). | H8: dotnet build Gprojet.slnx réussit sans avertissement ; dotnet sln Gprojet.slnx list affiche exactement 2 projets (Gprojet-Backend, Gprojet-Backend.Tests) ; dotnet test passe (test de fumée). Directory.Packages.props référence FluentAssertions 7.x ; .gitlab/ n'existe plus et .github/pull_request_template.md existe.
A9: 2 | B9: P1-T02 | C9: Tests d'architecture par espace de noms | D9: opus | E9: P1-T01 | F9: A_VALIDER | G9: les couches étant des dossiers d'un même projet, ces tests remplacent le compilateur comme garde. NetArchTest dans tests/Gprojet-Backend.Tests/Architecture/, une règle par interdiction entre espaces de noms Gprojet.Backend.* : Web ↛ Services / Repositories / Entities ; Orchestration ↛ implémentations de Repositories ; Services ↛ Contracts, Mapping, EF Core ; Entities ↛ toute autre couche sauf Common ; Contracts ↛ tout sauf BCL et FluentValidation (compilé dans le navigateur) ; types *Dto uniquement dans Contracts ; contrôleurs uniquement dans Web. Test « garde-fou » : des types de violation volontaire, définis dans le projet de test sous des espaces de noms simulés, sont bien détectés. | H9: dotnet test tests/Gprojet-Backend.Tests --filter Category=Architecture → tous verts, ≥ 10 règles ; le garde-fou prouve qu'une violation fait échouer la règle (assert inversé). | J9: H-019 (OUVERTE)
A10: 3 | B10: P1-T03 | C10: Common : primitives transverses | D10: sonnet | E10: P1-T01 | F10: A_VALIDER | G10: Result<T> / Result, exceptions métier (RegleMetierException, AccesRefuseException, IntrouvableException, ConflitException), PageRequete / PageResultat<T> (tri, filtre, taille max 200), ICurrentUser (Id agent, matricule, entité, rôles), IHorloge (testable), IGenerateurCode (codes lisibles). | H10: dotnet test tests/Gprojet-Backend.Tests --filter Category=Common → tests de Result, pagination (bornes, taille max) et horloge factice verts. | J10: H-020 (OUVERTE)
A11: 4 | B11: P1-T04 | C11: Entités du domaine (6 schémas) | D11: opus | E11: P1-T03 | F11: A_VALIDER | G11: EntiteAuditable (Id Guid v7, audit, suppression logique) et une classe par table de database/01-schema.sql, rangées par module (Organisation, Projets, Planification, Temps, Commun, Modelisation), avec propriétés de navigation, collections, et énumérations C# pour chaque CHECK … IN. Historique n'hérite pas d'EntiteAuditable (bigint, ajout seul). | H11: dotnet build OK ; test de réflexion : nombre de types entités = 60 et chaque énumération a les mêmes valeurs que la contrainte SQL correspondante (test paramétré lisant 01-schema.sql). | J11: H-021 (OUVERTE)
A12: 5 | B12: P1-T05 | C12: DbContext et configurations EF Core | D12: opus | E12: P1-T04 | F12: A_VALIDER | G12: GpDbContext (Npgsql, extension ltree), une IEntityTypeConfiguration<T> par entité : schéma, noms snake_case, types (numeric(p,s), ltree, jsonb, text[], inet), uuidv7() par défaut, contraintes CHECK, index uniques partiels (HasFilter), index GiST, colonne générée criticite, xmin (concurrence), filtre global !EstSupprime, conversions enum → texte. | H12: dotnet build OK ; dotnet ef dbcontext info réussit ; test unitaire : le modèle EF déclare 60 tables réparties dans les 6 schémas. | J12: H-022 (OUVERTE)
A13: 6 | B13: P1-T06 | C13: Migration initiale identique au schéma de référence | D13: opus | E13: P1-T05 | F13: EN_COURS | G13: migration InitialCreate (+ trigger d'ajout seul sur commun.historique et données de 02-donnees-reference.sql via migrationBuilder.Sql). Écrire scripts/comparer-schema.py : crée deux bases sur l'instance de test (l'une par 01-schema.sql, l'autre par dotnet ef database update), puis compare colonnes (type, nullabilité, défaut), contraintes, index (définition) et triggers via pg_catalog. Appliquer ensuite la migration à la base de développement gprojet (vide au départ ; connexion fournie par la variable ConnectionStrings__Gp, définie dans .claude/settings.local.json — ne jamais l'afficher ni la recopier). | H13: python scripts/comparer-schema.py → « 0 écart » ; toute différence est listée et fait échouer le script ; dotnet ef database update sur gprojet réussit et gprojet contient 60 tables dans les 6 schémas. | J13: H-023 (OUVERTE)
A14: 7 | B14: P1-T07 | C14: Intercepteurs : audit, suppression logique, historique chaîné | D14: sonnet | E14: P1-T06 | F14: NON_FAIT | G14: SaveChangesInterceptor qui renseigne cree_* / modifie_* depuis ICurrentUser et IHorloge, transforme un Remove en suppression logique, et écrit une ligne commun.historique par champ modifié avec l'empreinte sha256(empreinte_precedente + contenu) et un correlation_id par requête. | H14: tests d'intégration sur pg-test : création → audit rempli ; suppression → est_supprime = true et ligne invisible via le filtre global ; modification → lignes d'historique avec chaîne d'empreintes valide (recalcul) ; altérer une ligne en SQL direct est détecté par le vérificateur de chaîne.
A15: 8 | B15: P1-T08 | C15: Unit of Work et repositories de base | D15: sonnet | E15: P1-T06 | F15: NON_FAIT | G15: IUnitOfWork (CommitAsync, transaction explicite), classe de base interne RepositoryBase<T> (GetById, Ajouter, Supprimer logique, pagination), interfaces de repository par agrégat dans Repositories/ (exposées via des interfaces consommées par les Services). Gestion de DbUpdateConcurrencyException → ConflitException. | H15: tests d'intégration : commit atomique (échec au milieu → rien n'est écrit) ; deux mises à jour concurrentes de la même ligne → ConflitException.
A16: 9 | B16: P1-T09 | C16: Socle API : DI, erreurs, OpenAPI, logs, santé | D16: sonnet | E16: P1-T08 | F16: NON_FAIT | G16: Program.cs minimal ; méthodes d'extension d'enregistrement par couche (AddGpRepositories, AddGpServices, AddGpOrchestration…) ; middleware d'exceptions → ProblemDetails (400/403/404/409/500 sans fuite de détail en production) ; OpenAPI natif + Scalar en Development ; Serilog (console JSON) ; /health (live) et /health/ready (base) ; chaîne de connexion via configuration (ConnectionStrings:Gp), fournie en local par la variable d'environnement ConnectionStrings__Gp (base gprojet, définie dans .claude/settings.local.json) ; les tests n'utilisent jamais gprojet : instance jetable pg-test ou GP_TEST_CONNECTION, qui écrasent explicitement cette valeur. | H16: test d'intégration WebApplicationFactory : /health 200, /health/ready 200 sur pg-test, /openapi/v1.json 200, une IntrouvableException levée par un contrôleur de test → 404 au format application/problem+json ; dotnet run de l'API puis curl -s localhost:<port>/health/ready → 200 sur gprojet. | J16: H-004 (REPONDUE)
A17: 10 | B17: P1-T10 | C17: Authentification de développement et utilisateur courant | D17: sonnet | E17: P1-T09 | F17: NON_FAIT | G17: DevAuthHandler (schéma « Dev », actif uniquement en environnement Development/Test) qui lit l'en-tête X-Dev-Matricule, charge l'agent et ses rôles déduits (responsable d'entité, délégation active) ; implémentation ICurrentUser. Keycloak le remplacera en P18. | H17: tests d'intégration : sans en-tête → 401 ; matricule inconnu → 401 ; matricule valide → 200 et ICurrentUser renseigné ; en environnement Production le schéma « Dev » n'est pas enregistré.
A18: 11 | B18: P1-T11 | C18: Données de démonstration | D18: haiku | E18: P1-T06 | F18: NON_FAIT | G18: database/04-donnees-demo.sql : 1 direction, 3 divisions, 6 services, 25 agents fictifs (responsables nommés, fonctions, compétences), 2 délégations, quelques absences, jours fériés de l'année. Uniquement des noms fictifs. Option --demo dans pg-test.py demarrer. | H18: python scripts/pg-test.py demarrer --demo puis requêtes de comptage : 10 entités, 25 agents, 10 responsables ; chaque service a un parent division (requête ltree).

Sheet P2
A1: P2 · Socle frontend Blazor WebAssembly et BFF
A2: Objectif : projet unique Gprojet-Front servi par Gprojet-Backend (BFF intégré), charte et layout définitifs, couches front en place. Livrable : coquille navigable authentifiée (auth de dev).
A3: Statut phase | B3: NON_DEMARREE
A4: Modèle conseillé | B4: sonnet
A5: Avancement | B5: =IF(COUNTA(B8:B200)=0,0,(COUNTIF(F8:F200,"A_VALIDER")+COUNTIF(F8:F200,"VALIDE"))/COUNTA(B8:B200))
A6: ← Retour à l'ordre d'exécution
A7: Ordre | B7: Code | C7: Tâche | D7: Modèle | E7: Dépend de | F7: Statut | G7: Explication | H7: Test de validation | I7: Retours utilisateur | J7: Hypothèses liées
A8: 1 | B8: P2-T01 | C8: Projet Gprojet-Front, hébergement par le backend et tests bUnit | D8: sonnet | E8: — | F8: NON_FAIT | G8: un seul projet front src/Gprojet-Front/Gprojet-Front.csproj (Microsoft.NET.Sdk.BlazorWebAssembly, RootNamespace Gprojet.Front) ; les DTO y sont des fichiers liés (<Compile Include="..\Gprojet-Backend\Contracts\\*.cs" Link="Contracts\%(RecursiveDir)%(Filename)%(Extension)" />), jamais copiés ; Gprojet-Backend référence Gprojet-Front et le sert (UseBlazorFrameworkFiles, MapFallbackToFile("index.html"), paquet Microsoft.AspNetCore.Components.WebAssembly.Server) : même origine, pas de proxy ni de CORS ; tests tests/Gprojet-Front.Tests (bUnit). Arborescence des couches front : Api/, Services/, Models/, Pages/, Components/, Layouts/, State/, Auth/, Resources/, wwwroot/css/, wwwroot/fonts/, wwwroot/lib/, wwwroot/images/. | H8: dotnet build Gprojet.slnx OK et dotnet sln list affiche exactement 4 projets ; test d'intégration backend : GET / → 200 HTML contenant blazor.webassembly, GET /api/health → 200 ; un DTO de Gprojet-Backend/Contracts est utilisé dans le front (compilation) ; règle d'architecture : le front ne référence aucun autre code du backend.
A9: 2 | B9: P2-T02 | C9: Charte HCP : intégration de app.css et des ressources | D9: sonnet | E9: P2-T01 | F9: NON_FAIT | G9: appliquer design/charte-hcp/README.md. Copier design/charte-hcp/app.css dans wwwroot/css/app.css sans autre modification que le remplacement de l'@import Google Fonts par un @font-face local (Geist, licence OFL, fichiers dans wwwroot/fonts/). Créer wwwroot/css/app.gp.css (chargé après) : variantes de texte accessibles (--success-text, --warning-text, --danger-text, --info-text, --purple-text), badges des statuts GestionProjet (.status-badge.a-faire, .a-valider, .bloque, .valide…), classes manquantes, le tout à partir des variables de la charte. Auto-héberger Font Awesome Free 6 et Chart.js dans wwwroot/lib/ ; logo HCP dans wwwroot/images/. docs/DESIGN.md : renvoi vers la charte et inventaire des classes utilisées / ajoutées. | H9: un script compare design/charte-hcp/app.css et wwwroot/css/app.css : seule la ligne @import diffère ; grep -rE "https?://" src/Gprojet-Front/wwwroot/index.html src/Gprojet-Front/wwwroot/css ne renvoie rien (aucune ressource externe) ; aucune couleur hexadécimale dans Pages/, Components/, Layouts/ ni dans app.gp.css hors des 5 variables de texte documentées ; contraste de chaque variable de texte ≥ 4,5:1 (calcul dans un test). | J9: H-014 (REPONDUE)
A10: 3 | B10: P2-T03 | C10: Layout principal et navigation par rôle | D10: sonnet | E10: P2-T02 | F10: NON_FAIT | G10: MainLayout identique à celui de la GED HCP : .page > aside.sidebar (.sidebar-brand avec logo HCP, sections .nav-section-label, .nav-item avec icône et .nav-badge, pied .user-row) + .main-area > .topbar (bouton de repli, .breadcrumb-nav, .search-box avec raccourci Ctrl+K, notifications) + .content-area. Menu construit selon les rôles / politiques (AuthorizeView) ; repli du menu et mode mobile (classes sidebar-collapsed, mobile-open dans app.gp.css). | H10: tests bUnit : le rendu contient .page .sidebar, .main-area .topbar et .content-area ; un agent ne voit pas l'entrée « Portefeuille direction », un directeur la voit ; l'action de repli ajoute sidebar-collapsed.
A11: 4 | B11: P2-T04 | C11: Mouvement selon la charte (motion-design) | D11: sonnet | E11: P2-T02 | F11: NON_FAIT | G11: réutiliser uniquement les mouvements de la charte (0.15s ease pour les survols, fadeIn 0.25s / .animate-in pour les apparitions, 0.6s pour les barres de progression) ; motion-design sert à décider où les appliquer (apparition des pages et des listes, dialogues, repli du menu), pas à créer d'autres durées. Neutralisation complète sous prefers-reduced-motion: reduce dans app.gp.css. Documenter dans docs/DESIGN.md. | H11: app.gp.css contient un bloc @media (prefers-reduced-motion: reduce) qui neutralise transition et animation ; aucune durée autre que 0.1s, 0.15s, 0.25s, 0.6s dans les CSS du projet (grep) ; aucune bibliothèque JS d'animation ajoutée (git diff --stat sur wwwroot/lib vide).
A12: 5 | B12: P2-T05 | C12: Couche Api : clients HTTP typés | D12: sonnet | E12: P2-T01 | F12: NON_FAIT | G12: ApiClientBase (sérialisation System.Text.Json, conversion ProblemDetails → ApiException typée avec erreurs de validation, annulation), enregistrement des clients via IHttpClientFactory en adresses relatives (même origine que le backend), premier client SanteApiClient. | H12: tests unitaires avec HttpMessageHandler simulé : 200 → DTO ; 400 problem+json → ApiException contenant les erreurs par champ ; 404 → ApiException.Statut == 404.
A13: 6 | B13: P2-T06 | C13: Authentification côté front (BFF, mode dev) | D13: sonnet | E13: P2-T05 | F13: NON_FAIT | G13: endpoints BFF dans Gprojet-Backend/Web/Auth/ : /bff/login (dev : choix d'un matricule de démo), /bff/logout, /bff/user ; cookie HttpOnly, Secure, SameSite=Strict ; jeton anti-CSRF exigé sur les appels mutants ; BffAuthenticationStateProvider côté WASM ; page de connexion de développement. | H13: tests d'intégration BFF : /bff/user sans cookie → 401 ; après login dev → 200 avec matricule ; POST /api/... sans en-tête anti-CSRF → 400/403 ; test bUnit de AuthorizeView avec le provider.
A14: 7 | B14: P2-T07 | C14: État partagé et services front de base | D14: sonnet | E14: P2-T06 | F14: NON_FAIT | G14: State/UtilisateurCourantState, State/PerimetreState (entité, niveau, chemin), Services/NotificationUiService (snackbar), Services/ChargementService (indicateur global), gestion centralisée des ApiException (message utilisateur, journal console). | H14: tests bUnit : un composant abonné à PerimetreState se rafraîchit au changement ; une ApiException 403 affiche le message « Accès refusé » via le snackbar.
A15: 8 | B15: P2-T08 | C15: Internationalisation fr / en / ar (RTL) | D15: sonnet | E15: P2-T03 | F15: NON_FAIT | G15: Resources/*.resx (fr par défaut, en, ar), sélecteur de langue persistant (cookie BFF), dir="rtl" sur <html> et règles RTL dans app.gp.css (menu latéral à droite) pour l'arabe, formats de date et de nombre selon la culture. | H15: tests bUnit : en culture ar-MA le layout est rendu avec dir="rtl" ; un libellé du menu change selon la culture ; aucun texte en dur dans Layouts/ (contrôle : test qui échoue si une chaîne littérale française apparaît dans un .razor du layout).
A16: 9 | B16: P2-T09 | C16: Pages système | D16: haiku | E16: P2-T08 | F16: NON_FAIT | G16: pages Accueil (placeholder du tableau de bord), 404, Accès refusé, Erreur inattendue (avec identifiant de corrélation), Chargement initial. | H16: tests bUnit : chaque page se rend sans exception et contient son titre traduit.

Sheet P3
A1: P3 · Conteneurisation et intégration continue GitHub Actions
A2: Objectif : images Docker, environnement local complet par docker compose, intégration continue GitHub Actions sur le dépôt hajar-hamid-coder/gprojet. Livrable : docker compose up fonctionnel et .github/workflows/ci.yml. ⚠️ Nécessite Docker (hypothèse H-001).
A3: Statut phase | B3: NON_DEMARREE
A4: Modèle conseillé | B4: sonnet
A5: Avancement | B5: =IF(COUNTA(B8:B200)=0,0,(COUNTIF(F8:F200,"A_VALIDER")+COUNTIF(F8:F200,"VALIDE"))/COUNTA(B8:B200))
A6: ← Retour à l'ordre d'exécution
A7: Ordre | B7: Code | C7: Tâche | D7: Modèle | E7: Dépend de | F7: Statut | G7: Explication | H7: Test de validation | I7: Retours utilisateur | J7: Hypothèses liées
A8: 1 | B8: P3-T01 | C8: Dockerfile de l'application | D8: sonnet | E8: — | F8: NON_FAIT | G8: deploy/docker/Dockerfile unique, multi-étapes, qui publie Gprojet-Backend (le front publié est servi par le backend) (sdk:10.0 → aspnet:10.0 chiseled ou alpine), utilisateur non-root, HEALTHCHECK, variables ASPNETCORE_*, pas de secret dans l'image ; .dockerignore. | H8: docker build -f deploy/docker/Dockerfile -t gprojet:test . réussit ; docker run --rm gprojet:test id -u ≠ 0 ; l'image contient le front (wwwroot/_framework) ; taille d'image affichée dans la preuve. | J8: H-001 (REPONDUE, bloquante)
A9: 2 | B9: P3-T02 | C9: docker compose de développement | D9: sonnet | E9: P3-T01 | F9: NON_FAIT | G9: deploy/docker-compose.yml : postgres:18 (volume, base vide), service migrations (bundle EF dotnet ef migrations bundle qui crée le schéma — pas les scripts SQL, pour rester aligné sur les migrations), app (image unique), profil keycloak (préparé pour P18), réseau dédié, dépendances sur la santé ; deploy/.env.example sans valeur sensible. | H9: docker compose -f deploy/docker-compose.yml up -d --wait puis curl -s http://localhost:8080/api/health → 200 et curl -s http://localhost:8080/ → HTML ; docker compose down -v propre.
A10: 3 | B10: P3-T03 | C10: Tests en CI avec PostgreSQL de service | D10: sonnet | E10: — | F10: NON_FAIT | G10: rendre les tests d'intégration indépendants de pg-test.py via la variable GP_TEST_CONNECTION (si définie : base fournie par la CI ; sinon : instance locale jetable). Fixture xUnit commune. | H10: dotnet test local (instance jetable) vert ; avec GP_TEST_CONNECTION pointant sur l'instance démarrée manuellement, les mêmes tests passent.
A11: 4 | B11: P3-T04 | C11: Workflow GitHub Actions | D11: sonnet | E11: P3-T01, P3-T03 | F11: NON_FAIT | G11: .github/workflows/ci.yml déclenché sur push et pull request : jobs build, test (service postgres:18, GP_TEST_CONNECTION, rapport de tests et couverture publiés comme artefacts), qualite (dotnet format --verify-no-changes), securite (CodeQL C#, dependency-review sur les pull requests, scan d'image Trivy), paquet (build et push de l'image vers GitHub Container Registry ghcr.io sur main et les tags, avec GITHUB_TOKEN), deploiement (workflow_dispatch + environnement protégé, préparé pour P13). Cache NuGet, versions d'actions épinglées. Vérifier que les modèles .github/ (faits en P1-T01) sont cohérents avec le workflow. | H11: python scripts/verifier-ci.py (à écrire, parse YAML) confirme les 6 jobs, leurs dépendances, le service PostgreSQL et l'absence de secret en clair ; les modèles .github/ sont présents. L'exécution réelle sur GitHub se constate après le push de l'utilisateur (signalé dans le bilan de phase). | J11: H-002 (REPONDUE)
A12: 5 | B12: P3-T05 | C12: Documentation de déploiement local | D12: haiku | E12: P3-T02, P3-T04 | F12: NON_FAIT | G12: docs/DEPLOIEMENT.md : prérequis, variables, démarrage compose, migrations, dépannage, description du workflow GitHub Actions, des secrets à créer (Settings → Secrets and variables → Actions) et de la publication d'image sur ghcr.io. | H12: le document contient les sections Prérequis, Démarrage, Variables, Pipeline, Dépannage ; chaque commande citée existe dans le dépôt.

Sheet P4
A1: P4 · Module Organisation et périmètre hiérarchique
A2: Objectif : organigramme, agents, délégations, absences, et le service de périmètre sur lequel repose toute la sécurité des données. Livrable : module Organisation complet (API + pages).
A3: Statut phase | B3: NON_DEMARREE
A4: Modèle conseillé | B4: sonnet
A5: Avancement | B5: =IF(COUNTA(B8:B200)=0,0,(COUNTIF(F8:F200,"A_VALIDER")+COUNTIF(F8:F200,"VALIDE"))/COUNTA(B8:B200))
A6: ← Retour à l'ordre d'exécution
A7: Ordre | B7: Code | C7: Tâche | D7: Modèle | E7: Dépend de | F7: Statut | G7: Explication | H7: Test de validation | I7: Retours utilisateur | J7: Hypothèses liées
A8: 1 | B8: P4-T01 | C8: Service de périmètre et rôles déduits | D8: opus | E8: — | F8: NON_FAIT | G8: PerimetreService : rôle hiérarchique déduit (directeur / chef de division / chef de service / agent) depuis l'entité dirigée et les délégations actives à la date du jour ; chemin ltree du périmètre ; IPerimetreCourant injectable ; extension IQueryable<Projet>.DansPerimetre() et équivalents Phase / Tâche / Ticket / Saisie (membre du projet inclus) ; politiques EstChef, EstDirecteur… | H8: tests unitaires et d'intégration (données de démo) : matrice de 12 cas (4 rôles × visibilité au-dessus / à côté / en dessous) ; délégation hors dates → aucun droit ; agent membre d'un projet d'un autre service → voit ce projet uniquement.
A9: 2 | B9: P4-T02 | C9: Organigramme : API | D9: sonnet | E9: P4-T01 | F9: NON_FAIT | G9: cas d'usage complets (DTO, validateurs, orchestrateur, service, repository, contrôleur) : créer / modifier / désactiver une entité, déplacer une entité (recalcul du chemin de tout le sous-arbre en une requête), nommer un responsable. Règles : service → parent division, division → parent direction ; un agent ne dirige qu'une entité. | H9: tests d'intégration : déplacement d'une division → chemins de ses services et projets portés mis à jour ; service rattaché à une direction → 400 ; double responsabilité → 409.
A10: 3 | B10: P4-T03 | C10: Agents, rattachements et compétences : API | D10: sonnet | E10: P4-T02 | F10: NON_FAIT | G10: CRUD agents ; mutation (clôture du rattachement, ouverture du nouveau, mise à jour de entite_id) ; fonction ; compétences avec niveau ; recherche paginée (nom, matricule, entité, compétence). | H10: tests : mutation → 2 rattachements dont 1 ouvert ; tentative de second rattachement ouvert → refus ; recherche par compétence renvoie les bons agents.
A11: 4 | B11: P4-T04 | C11: Délégations, absences et calendrier : API | D11: sonnet | E11: P4-T01 | F11: NON_FAIT | G11: délégations (période, droits, entité ; seul le responsable de l'entité délègue), absences (types, demi-journée), jours fériés ; service CalendrierService.JoursOuvres(agent, période) utilisé plus tard par le CPM et le plan de charge. | H11: tests : délégation active → le délégataire obtient PeutCreerProjet ; JoursOuvres exclut week-ends, fériés et absences (cas avec demi-journée = 0,5).
A12: 5 | B12: P4-T05 | C12: Pages organigramme | D12: sonnet | E12: P4-T02 | F12: NON_FAIT | G12: arbre interactif (composant maison ArbreOrganisation au style de la charte) avec responsable et effectif, fiche entité (membres, projets portés), formulaires création / déplacement / nomination ; écrans selon la charte HCP (design/charte-hcp/README.md). | H12: tests bUnit : l'arbre affiche 3 niveaux à partir de données simulées ; le formulaire refuse un parent incohérent (message de validation partagé) ; les actions sont masquées pour un agent.
A13: 6 | B13: P4-T06 | C13: Pages agents | D13: sonnet | E13: P4-T03 | F13: NON_FAIT | G13: liste filtrable et paginée, fiche agent (rattachements, compétences, absences, projets), dialogue de mutation, édition des compétences. | H13: tests bUnit : filtre par entité ; dialogue de mutation → appel du service avec les bons paramètres ; affichage de l'historique des rattachements.
A14: 7 | B14: P4-T07 | C14: Pages délégations, absences et calendrier | D14: sonnet | E14: P4-T04 | F14: NON_FAIT | G14: gestion des délégations par le chef (avec bandeau « vous agissez par délégation de … »), saisie des absences, calendrier des jours fériés (admin). | H14: tests bUnit : le bandeau de délégation apparaît quand l'utilisateur agit par délégation ; validation des dates (fin ≥ début).
A15: 8 | B15: P4-T08 | C15: Documentation fonctionnelle du module | D15: haiku | E15: P4-T05, P4-T06, P4-T07 | F15: NON_FAIT | G15: docs/modules/organisation.md : règles métier, rôles et droits, endpoints (lien OpenAPI), écrans. | H15: le document liste chaque endpoint du module (comparaison automatique avec /openapi/v1.json via un petit script ou test).

Sheet P5
A1: P5 · Projets et affectation en cascade
A2: Objectif : création réservée aux chefs, cascade Directeur → Division → Service → Personnel, portefeuille filtré. Livrable : module Projets complet et étanche entre périmètres.
A3: Statut phase | B3: NON_DEMARREE
A4: Modèle conseillé | B4: opus
A5: Avancement | B5: =IF(COUNTA(B8:B200)=0,0,(COUNTIF(F8:F200,"A_VALIDER")+COUNTIF(F8:F200,"VALIDE"))/COUNTA(B8:B200))
A6: ← Retour à l'ordre d'exécution
A7: Ordre | B7: Code | C7: Tâche | D7: Modèle | E7: Dépend de | F7: Statut | G7: Explication | H7: Test de validation | I7: Retours utilisateur | J7: Hypothèses liées
A8: 1 | B8: P5-T01 | C8: Référentiels : types de projet et modèles de phases | D8: sonnet | E8: — | F8: NON_FAIT | G8: API + pages d'administration des types de projet et de leurs modèles de phases (ordre, critères, mode d'enchaînement). | H8: tests : réordonnancement des modèles de phases sans trou ni doublon ; suppression d'un type utilisé → 409.
A9: 2 | B9: P5-T02 | C9: Création de projet | D9: opus | E9: P5-T01 | F9: NON_FAIT | G9: réservée aux chefs et délégataires ; code PRJ-AAAA-NNNN sans collision en concurrence (séquence annuelle) ; entité créatrice, chemin initial ; instanciation des phases depuis le modèle du type ; statut BROUILLON → EN_AFFECTATION (direction / division) ou EN_COURS (service). | H9: tests : un agent → 403 ; un chef de service → projet EN_COURS porté par son service ; 20 créations parallèles → 20 codes distincts ; les phases du modèle DEV sont créées (7).
A10: 3 | B10: P5-T03 | C10: Affectation en cascade | D10: opus | E10: P5-T02 | F10: NON_FAIT | G10: affecter (cible = enfant direct de la source), accepter (met à jour entité porteuse + chemin), renvoyer (motif obligatoire, revient à l'émetteur), réaffecter, annuler ; chaîne precedente_id ; une seule affectation active ; événements de domaine pour notifications (consommés en P9) ; historique. | H10: tests couvrant chaque transition et chaque refus (cible non enfant, double affectation, renvoi sans motif, acteur hors périmètre) ; scénario complet directeur → division → service → acceptation : chemin final = chemin du service.
A11: 4 | B11: P5-T04 | C11: Équipe projet | D11: sonnet | E11: P5-T03 | F11: NON_FAIT | G11: le chef du service porteur ajoute / retire des membres (agents de son service, prestataires et observateurs autorisés), quotas, désignation du chef de projet. | H11: tests : agent d'un autre service → refus ; somme des quotas d'un agent sur ses projets > 100 % → avertissement renvoyé (pas de blocage) ; chef de projet obligatoirement membre.
A12: 5 | B12: P5-T05 | C12: Jalons et registre RAID | D12: sonnet | E12: P5-T02 | F12: NON_FAIT | G12: CRUD jalons (lien phase optionnel, retard calculé) et éléments RAID (criticité, responsable, échéance, statut). | H12: tests : un risque sans probabilité → 400 ; jalon dépassé non atteint → statut EN_RETARD calculé.
A13: 6 | B13: P5-T06 | C13: Politiques d'autorisation et tests anti-fuite | D13: opus | E13: P5-T03, P5-T04 | F13: NON_FAIT | G13: politiques PeutCreerProjet, PeutAffecterDivision, PeutAffecterService, PeutGererEquipe, PeutVoirProjet appliquées à tous les contrôleurs Projets ; un projet hors périmètre renvoie 404 (pas 403, pour ne pas révéler son existence). | H13: suite de tests d'intégration paramétrée parcourant tous les endpoints Projets avec 4 profils : aucun accès hors périmètre (404), aucune liste ne contient de projet hors périmètre.
A14: 7 | B14: P5-T07 | C14: Pages portefeuille et création | D14: sonnet | E14: P5-T06 | F14: NON_FAIT | G14: portefeuille (grille filtrable : statut, type, priorité, météo, entité), assistant de création en étapes, fiche projet à onglets (synthèse, phases, équipe, jalons, RAID, historique). | H14: tests bUnit : le bouton « Nouveau projet » est absent pour un agent ; l'assistant valide chaque étape avant la suivante.
A15: 8 | B15: P5-T08 | C15: Pages d'affectation | D15: sonnet | E15: P5-T07 | F15: NON_FAIT | G15: file « Projets à affecter » par chef, dialogues affecter / accepter / renvoyer, frise de la chaîne d'affectation. | H15: tests bUnit : le renvoi exige un motif ; la frise affiche les étapes dans l'ordre chronologique.
A16: 9 | B16: P5-T09 | C16: Pages équipe, jalons, RAID | D16: sonnet | E16: P5-T07 | F16: NON_FAIT | G16: onglets de la fiche projet : gestion de l'équipe, jalons, matrice des risques (probabilité × impact). | H16: tests bUnit : la matrice place un risque P4×I5 dans la bonne cellule ; seuls les membres du service sont proposés dans l'ajout d'équipe.
A17: 10 | B17: P5-T10 | C17: Tâches planifiées et alerte de non-affectation | D17: sonnet | E17: P5-T03 | F17: NON_FAIT | G17: infrastructure de jobs (Quartz.NET, persistance PostgreSQL) dans Infrastructure/ ; job quotidien : projet en attente d'affectation au-delà de alerte.delai_affectation_jours → événement d'alerte au chef concerné. | H17: test avec IHorloge simulée : projet affecté il y a 6 jours (seuil 5) → 1 alerte ; 4 jours → 0.

Sheet P6
A1: P6 · Planification et ordonnancement
A2: Objectif : phases, tâches, tickets, workflows, dépendances, chemin critique. Livrable : planification complète avec Gantt et Kanban.
A3: Statut phase | B3: NON_DEMARREE
A4: Modèle conseillé | B4: opus
A5: Avancement | B5: =IF(COUNTA(B8:B200)=0,0,(COUNTIF(F8:F200,"A_VALIDER")+COUNTIF(F8:F200,"VALIDE"))/COUNTA(B8:B200))
A6: ← Retour à l'ordre d'exécution
A7: Ordre | B7: Code | C7: Tâche | D7: Modèle | E7: Dépend de | F7: Statut | G7: Explication | H7: Test de validation | I7: Retours utilisateur | J7: Hypothèses liées
A8: 1 | B8: P6-T01 | C8: Workflows configurables | D8: sonnet | E8: — | F8: NON_FAIT | G8: administration des workflows (statuts, catégories, couleurs, statut initial, transitions et rôles autorisés) ; service WorkflowService.PeutTransiter(element, vers, utilisateur). | H8: tests : transition non déclarée → refus ; transition réservée CHEF_PROJET refusée à un membre ; un workflow sans statut TERMINE est invalide.
A9: 2 | B9: P6-T02 | C9: Phases : gestion et ordre | D9: sonnet | E9: P6-T01 | F9: NON_FAIT | G9: CRUD phases, réordonnancement transactionnel sans trou, mode d'enchaînement, critères, livrables. | H9: tests : déplacer la phase 4 en position 2 → ordres 1..n continus ; mode CHEVAUCHEMENT sans pourcentage → 400.
A10: 3 | B10: P6-T03 | C10: Validation de fin de phase (gate) | D10: opus | E10: P6-T02 | F10: NON_FAIT | G10: soumission d'une phase, circuit de validation multi-niveaux (chef de service puis chef de division selon paramétrage), rejet motivé → nouveau tour, règle de démarrage de N+1 selon le mode d'enchaînement. | H10: tests : N+1 ne démarre pas tant que N n'est pas validée (mode séquentiel) ; démarre à 60 % si chevauchement à 50 % ; rejet → tour 2 sans perdre le tour 1.
A11: 4 | B11: P6-T04 | C11: Tâches : gestion, WBS, estimation | D11: sonnet | E11: P6-T02 | F11: NON_FAIT | G11: CRUD tâches, code WBS recalculé, ordre, mode d'exécution, responsable (membre du projet), estimation à trois points (PERT : (O + 4M + P) / 6), récurrence. | H11: tests : WBS « 2.3 » après déplacement ; estimation O=4, M=6, P=14 → 7 h ; responsable non membre → 400.
A12: 5 | B12: P6-T05 | C12: Dépendances, cycles et contrôle de démarrage | D12: opus | E12: P6-T04 | F12: NON_FAIT | G12: dépendances FD / DD / FF / DF avec délai ; détection de cycle (parcours en profondeur sur le graphe du projet) ; démarrage d'une tâche : mode BLOQUANT → refus si prédécesseur non terminé ; mode SOUPLE → dérogation justifiée obligatoire. | H12: tests : A→B→C puis C→A → refus « cycle » ; démarrer B avant A en mode bloquant → refus ; en mode souple sans justification → 400, avec → OK et dérogation enregistrée.
A13: 6 | B13: P6-T06 | C13: Moteur de chemin critique (CPM) | D13: opus | E13: P6-T05 | F13: NON_FAIT | G13: passes avant et arrière sur jours ouvrés (calendrier, fériés, absences du responsable, capacité), 4 types de liens et délais ; dates prévues, marges totale et libre, est_critique ; recalcul en cascade lors d'un glissement + alerte au chef de projet. | H13: tests sur 3 réseaux de référence avec résultats calculés à la main (dont un manuel de gestion de projet) : dates, marges et chemin critique exacts ; glissement de 3 jours d'une tâche critique → date de fin projet +3 jours ouvrés.
A14: 7 | B14: P6-T07 | C14: Tickets | D14: sonnet | E14: P6-T01, P6-T04 | F14: NON_FAIT | G14: CRUD tickets, numérotation atomique (prochain_numero_ticket), types et workflows, rang, liens, tickets bloquants empêchant la clôture de la tâche. | H14: tests : 50 créations parallèles → numéros 1..50 sans trou ni doublon ; clôturer une tâche avec un ticket bloquant ouvert → 409.
A15: 8 | B15: P6-T08 | C15: Remontée d'avancement et de charge | D15: sonnet | E15: P6-T07 | F15: NON_FAIT | G15: recalcul des caches ticket → tâche → phase → projet (charge estimée, reste à faire, avancement) à chaque modification, dans la même transaction. | H15: tests : passer un ticket en catégorie TERMINE met à jour l'avancement de la tâche, de la phase et du projet avec les valeurs attendues.
A16: 9 | B16: P6-T09 | C16: Baselines | D16: sonnet | E16: P6-T06 | F16: NON_FAIT | G16: figer le planning (photo des dates et charges), comparer planifié / baseline / réel, écarts par tâche et par phase. | H16: tests : après glissement, la comparaison montre l'écart exact par tâche ; deux baselines coexistent.
A17: 10 | B17: P6-T10 | C17: Pages liste, Kanban et fiches | D17: sonnet | E17: P6-T08 | F17: NON_FAIT | G17: vue liste hiérarchique (phase > tâche > ticket), Kanban des tickets par statut avec glisser-déposer respectant les transitions, fiches tâche et ticket, « Ma prochaine tâche » et « Mes tickets ». | H17: tests bUnit : un dépôt vers une colonne non autorisée est refusé visuellement et non envoyé ; « Ma prochaine tâche » affiche la tâche prête la plus prioritaire.
A18: 11 | B18: P6-T11 | C18: Gantt et réseau PERT | D18: opus | E18: P6-T06, P6-T10 | F18: NON_FAIT | G18: composant Gantt (bibliothèque JS sous licence libre via JS Interop, choix consigné en hypothèse) : barres, dépendances, jalons, chemin critique en surbrillance, déplacement → recalcul ; vue PERT (graphe) ; accessibilité clavier minimale et alternative tabulaire. | H18: test bUnit de l'enveloppe (données transmises au module JS) ; test d'intégration : le déplacement envoie la bonne requête et le recalcul revient ; vérification manuelle décrite dans la preuve (capture). | J18: H-005 (OUVERTE)
A19: 12 | B19: P6-T12 | C19: Documentation du module | D19: haiku | E19: P6-T11 | F19: NON_FAIT | G19: docs/modules/planification.md : règles d'ordonnancement, modes, CPM (formules), workflows par défaut. | H19: le document contient les sections Ordonnancement, CPM, Workflows, Écrans et un exemple chiffré.

Sheet P7
A1: P7 · Coût en temps
A2: Objectif : saisie, validation hiérarchique, prévu / consommé / reste à faire, plan de charge. Livrable : module Temps complet.
A3: Statut phase | B3: NON_DEMARREE
A4: Modèle conseillé | B4: sonnet
A5: Avancement | B5: =IF(COUNTA(B8:B200)=0,0,(COUNTIF(F8:F200,"A_VALIDER")+COUNTIF(F8:F200,"VALIDE"))/COUNTA(B8:B200))
A6: ← Retour à l'ordre d'exécution
A7: Ordre | B7: Code | C7: Tâche | D7: Modèle | E7: Dépend de | F7: Statut | G7: Explication | H7: Test de validation | I7: Retours utilisateur | J7: Hypothèses liées
A8: 1 | B8: P7-T01 | C8: Référentiels et paramètres du temps | D8: haiku | E8: — | F8: NON_FAIT | G8: administration des catégories d'activité (projet / hors projet) et des paramètres (heures par jour, seuils). | H8: tests : désactiver une catégorie utilisée la masque à la saisie sans casser l'historique.
A9: 2 | B9: P7-T02 | C9: Feuilles de temps et saisies | D9: sonnet | E9: P7-T01 | F9: NON_FAIT | G9: feuille hebdomadaire (créée à la demande), saisies avec règles : catégorie projet ⇒ tâche obligatoire, ticket appartenant à la tâche, total ≤ 24 h par jour, agent membre du projet, lecture seule si feuille validée ou verrouillée. | H9: tests pour chaque règle (cas nominal + refus) ; saisie hors projet acceptée sans tâche.
A10: 3 | B10: P7-T03 | C10: Chronomètre | D10: sonnet | E10: P7-T02 | F10: NON_FAIT | G10: démarrer / arrêter un chronomètre depuis un ticket (un seul actif par agent), conversion en saisie arrondie au quart d'heure. | H10: tests : 1 h 08 → 1,25 h ; second chronomètre → arrêt automatique du premier.
A11: 4 | B11: P7-T04 | C11: Circuit de validation des temps | D11: opus | E11: P7-T02 | F11: NON_FAIT | G11: soumettre, valider / rejeter (motif) par le chef du service de rattachement à la date de la semaine (historique des rattachements, délégations), verrouillage de période, consolidation par le chef de division. | H11: tests : agent muté en cours de mois → la semaine antérieure est validée par l'ancien chef ; rejet sans motif → 400 ; période verrouillée → modification refusée.
A12: 5 | B12: P7-T05 | C12: Prévu, consommé, reste à faire et alertes | D12: sonnet | E12: P7-T04 | F12: NON_FAIT | G12: agrégation des temps validés en jours-homme par tâche / phase / projet, écarts (jours, %), reprévision de la date de fin selon la vélocité réelle, job d'alerte au-delà du seuil de charge consommée. | H12: tests chiffrés : estimé 10 j, consommé 8,5 j → 85 % → alerte (seuil 80) ; reprévision conforme à la formule documentée.
A13: 6 | B13: P7-T06 | C13: Plan de charge et taux d'occupation | D13: sonnet | E13: P7-T05 | F13: NON_FAIT | G13: charge affectée vs capacité par agent, service, division, direction (jours ouvrés, absences, quotas) ; taux d'occupation incluant le hors-projet ; surcharge / sous-charge. | H13: tests chiffrés sur les données de démo : taux d'occupation d'un service = valeur calculée à la main dans le test.
A14: 7 | B14: P7-T07 | C14: Pages saisie, chronomètre et validation | D14: sonnet | E14: P7-T04 | F14: NON_FAIT | G14: grille hebdomadaire (lignes tâches / tickets, colonnes jours, totaux), widget chronomètre dans la barre d'application, file de validation des chefs. | H14: tests bUnit : total journalier > 24 h signalé avant envoi ; la file de validation n'affiche que les agents du périmètre.
A15: 8 | B15: P7-T08 | C15: Page plan de charge | D15: sonnet | E15: P7-T06 | F15: NON_FAIT | G15: carte de chaleur agents × semaines (couleurs de surcharge du thème), filtres par entité et compétence. | H15: tests bUnit : une cellule à 120 % porte la classe « surcharge » ; filtre par compétence.

Sheet P8
A1: P8 · Reporting par niveau hiérarchique
A2: Objectif : tableaux de bord Directeur / Division / Service / Agent avec drill-down et exports. Livrable : reporting complet, rapide et étanche.
A3: Statut phase | B3: NON_DEMARREE
A4: Modèle conseillé | B4: sonnet
A5: Avancement | B5: =IF(COUNTA(B8:B200)=0,0,(COUNTIF(F8:F200,"A_VALIDER")+COUNTIF(F8:F200,"VALIDE"))/COUNTA(B8:B200))
A6: ← Retour à l'ordre d'exécution
A7: Ordre | B7: Code | C7: Tâche | D7: Modèle | E7: Dépend de | F7: Statut | G7: Explication | H7: Test de validation | I7: Retours utilisateur | J7: Hypothèses liées
A8: 1 | B8: P8-T01 | C8: Requêtes de reporting | D8: opus | E8: — | F8: NON_FAIT | G8: requêtes de lecture dédiées (projections ou SQL) filtrées par périmètre : synthèse portefeuille (statut, type, priorité, météo), comparatifs divisions / services, charges et écarts, retards, affectations en attente et délais d'affectation, validations en attente, jalons à 30/60/90 jours, risques et vulnérabilités critiques. | H8: tests chiffrés sur un jeu de données dédié (valeurs attendues écrites dans le test) ; un chef de division ne reçoit aucune ligne d'une autre division ; chaque requête < 300 ms sur ce jeu (mesure dans le test).
A9: 2 | B9: P8-T02 | C9: Tableau de bord Directeur | D9: sonnet | E9: P8-T01 | F9: NON_FAIT | G9: indicateurs de synthèse, comparatif des divisions (graphiques), projets non affectés, retards, validations en attente, jalons, risques ; cartes .stat-card, graphiques Chart.js aux couleurs de la charte, ergonomie via ui-ux-pro-max. | H9: tests bUnit : chaque widget gère les états vide / chargement / erreur ; les valeurs affichées correspondent au DTO fourni.
A10: 3 | B10: P8-T03 | C10: Tableau de bord Chef de division | D10: sonnet | E10: P8-T01 | F10: NON_FAIT | G10: mêmes indicateurs sur la division, comparatif des services, projets à affecter, charge par service. | H10: tests bUnit analogues à P8-T02.
A11: 4 | B11: P8-T04 | C11: Tableau de bord Chef de service | D11: sonnet | E11: P8-T01 | F11: NON_FAIT | G11: projets du service, équipes à constituer, charge par agent, feuilles à valider, tâches bloquées et critiques, tickets en retard. | H11: tests bUnit analogues à P8-T02.
A12: 5 | B12: P8-T05 | C12: Tableau de bord Agent | D12: sonnet | E12: P8-T01 | F12: NON_FAIT | G12: ma prochaine tâche, mes tickets par priorité et ordre, temps de la semaine, échéances. | H12: tests bUnit analogues à P8-T02.
A13: 6 | B13: P8-T06 | C13: Navigation de drill-down | D13: sonnet | E13: P8-T02, P8-T03, P8-T04 | F13: NON_FAIT | G13: composant fil d'Ariane Direction → Division → Service → Projet → Phase → Tâche → Ticket → Agent, conservation des filtres dans l'URL, retour arrière cohérent. | H13: tests bUnit : cliquer sur une division filtre le tableau de bord et ajoute un niveau au fil d'Ariane ; l'URL contient les filtres.
A14: 7 | B14: P8-T07 | C14: Exports Excel et PDF | D14: sonnet | E14: P8-T01 | F14: NON_FAIT | G14: export Excel (bibliothèque libre) et PDF au format officiel (en-tête, logo de l'entité) des rapports standard ; choix des bibliothèques et licences consigné en hypothèse. | H14: tests : le fichier Excel contient les colonnes et le nombre de lignes attendus ; le PDF est lisible (extraction du texte contient le titre du rapport). | J14: H-006 (OUVERTE) H-007 (OUVERTE)
A15: 8 | B15: P8-T08 | C15: Rapports planifiés par e-mail | D15: sonnet | E15: P8-T07 | F15: NON_FAIT | G15: job hebdomadaire / mensuel envoyant à chaque chef le rapport de son périmètre ; envoi SMTP via Infrastructure/ (en développement : dépôt dans un dossier de fichiers .eml). | H15: test : exécution du job en développement → un .eml par chef, contenant uniquement les projets de son périmètre.

Sheet P9
A1: P9 · Collaboration et services transverses
A2: Objectif : commentaires, pièces jointes, notifications temps réel, historique consultable. Livrable : collaboration sur tout élément.
A3: Statut phase | B3: NON_DEMARREE
A4: Modèle conseillé | B4: sonnet
A5: Avancement | B5: =IF(COUNTA(B8:B200)=0,0,(COUNTIF(F8:F200,"A_VALIDER")+COUNTIF(F8:F200,"VALIDE"))/COUNTA(B8:B200))
A6: ← Retour à l'ordre d'exécution
A7: Ordre | B7: Code | C7: Tâche | D7: Modèle | E7: Dépend de | F7: Statut | G7: Explication | H7: Test de validation | I7: Retours utilisateur | J7: Hypothèses liées
A8: 1 | B8: P9-T01 | C8: Commentaires et mentions | D8: sonnet | E8: — | F8: NON_FAIT | G8: commentaires polymorphes (projet, phase, tâche, ticket, diagramme…), fils de discussion, @mention d'un agent du projet, édition marquée, droits selon le périmètre de l'élément commenté. | H8: tests : commenter un ticket hors périmètre → 404 ; une mention crée un événement de notification ; un fil de 3 niveaux est restitué dans l'ordre.
A9: 2 | B9: P9-T02 | C9: Pièces jointes | D9: sonnet | E9: — | F9: NON_FAIT | G9: téléversement en flux (taille max et types autorisés paramétrés), stockage disque configurable hors racine web, empreinte SHA-256, téléchargement contrôlé par le périmètre ; point d'extension pour un antivirus (hypothèse). | H9: tests : fichier > taille max → 413 ; extension interdite → 400 ; l'empreinte stockée correspond au fichier ; téléchargement hors périmètre → 404. | J9: H-008 (OUVERTE)
A10: 3 | B10: P9-T03 | C10: Notifications temps réel | D10: sonnet | E10: P9-T01 | F10: NON_FAIT | G10: consommation des événements de domaine (affectation, mention, validation, échéance…) → notifications en base, diffusion SignalR, centre de notifications côté front, préférences par type, résumé quotidien par e-mail. | H10: test d'intégration SignalR : une affectation provoque la réception du message par le client du chef ciblé et pas par un autre ; test bUnit du compteur non lu.
A11: 4 | B11: P9-T04 | C11: Abonnements (observateurs) | D11: sonnet | E11: P9-T03 | F11: NON_FAIT | G11: nouvelle table commun.abonnement (migration + mise à jour du MLD), s'abonner / se désabonner d'un élément, notifications aux abonnés. | H11: python scripts/comparer-schema.py toujours à 0 écart après mise à jour de database/01-schema.sql ; un abonné reçoit la notification d'un changement de statut.
A12: 5 | B12: P9-T05 | C12: Historique et vérification d'intégrité | D12: sonnet | E12: — | F12: NON_FAIT | G12: frise d'historique par élément (qui, quoi, quand, avant / après), endpoint d'administration qui vérifie la chaîne d'empreintes et signale la première rupture. | H12: tests : la frise d'un ticket modifié 3 fois contient 3 entrées ; une altération SQL directe est détectée à la bonne ligne.

Sheet P10
A1: P10 · Modélisation et diagrammes
A2: Objectif : métamodèle éditable, cohérence, transformation MCD → MLD → SQL, éditeurs de diagrammes. Livrable : module Modélisation, capable de reproduire le MLD de la plateforme.
A3: Statut phase | B3: NON_DEMARREE
A4: Modèle conseillé | B4: opus
A5: Avancement | B5: =IF(COUNTA(B8:B200)=0,0,(COUNTIF(F8:F200,"A_VALIDER")+COUNTIF(F8:F200,"VALIDE"))/COUNTA(B8:B200))
A6: ← Retour à l'ordre d'exécution
A7: Ordre | B7: Code | C7: Tâche | D7: Modèle | E7: Dépend de | F7: Statut | G7: Explication | H7: Test de validation | I7: Retours utilisateur | J7: Hypothèses liées
A8: 1 | B8: P10-T01 | C8: API du métamodèle | D8: sonnet | E8: — | F8: NON_FAIT | G8: CRUD modèles (versions), modules, entités, attributs, énumérations et valeurs, associations et pattes, index, méthodes et paramètres ; validations (noms techniques snake_case, rôle obligatoire sur une association réflexive, propriétaire unique d'un attribut). | H8: tests d'intégration couvrant chaque ressource et chaque règle de validation.
A9: 2 | B9: P10-T02 | C9: Contrôle de cohérence d'un modèle | D9: opus | E9: P10-T01 | F9: NON_FAIT | G9: rapport de cohérence : entité sans identifiant, association à moins de 2 pattes, cardinalités manquantes, héritage cyclique, noms en conflit (table / colonne générée), attribut libellé absent, énumération vide. | H9: un modèle de test contenant volontairement 7 défauts → rapport listant exactement ces 7 défauts ; le modèle de la plateforme → 0 défaut.
A10: 3 | B10: P10-T03 | C10: Transformation MCD → MLD (règles R1 à R10) | D10: opus | E10: P10-T02 | F10: NON_FAIT | G10: générer table_bd, colonne, cle_etrangere à partir du modèle selon R1…R10 (../Documentation/03-mcd.md §8), avec traçabilité vers la source et conservation des surcharges manuelles (est_surchargee) signalées en cas de conflit. | H10: un test par règle (10 tests minimum) avec MLD attendu explicite ; régénération après surcharge → surcharge conservée et conflit signalé.
A11: 4 | B11: P10-T04 | C11: Génération SQL (MPD) PostgreSQL | D11: opus | E11: P10-T03 | F11: NON_FAIT | G11: produire le script DDL (schémas, tables, colonnes typées via correspondance_type, PK, FK, CHECK d'énumérations, index uniques partiels, colonnes techniques selon options) dans l'ordre des dépendances. | H11: le SQL généré pour un modèle de test s'exécute sans erreur sur l'instance pg-test ; idempotence textuelle (deux générations identiques).
A12: 5 | B12: P10-T05 | C12: Import / export et rétro-ingénierie | D12: opus | E12: P10-T04 | F12: NON_FAIT | G12: export / import d'un modèle complet en JSON versionné ; rétro-ingénierie d'une base PostgreSQL existante (pg_catalog) → MLD → MCD (tables d'association reconnues comme associations N:N). | H12: aller-retour export → import → export identique ; rétro-ingénierie de la base de référence → 60 tables et associations N:N reconnues (entite_interface, etc.).
A13: 6 | B13: P10-T06 | C13: Dogfooding : la plateforme se décrit elle-même | D13: opus | E13: P10-T05 | F13: NON_FAIT | G13: construire le modèle de la plateforme (par rétro-ingénierie puis ajustements : rôles, natures d'association, options), générer son SQL et le comparer à database/01-schema.sql avec scripts/comparer-schema.py. Consigner chaque écart irréductible. | H13: python scripts/comparer-schema.py --gauche database/01-schema.sql --droite <sql généré> → 0 écart, ou écarts listés et justifiés dans docs/modules/modelisation.md.
A14: 7 | B14: P10-T07 | C14: Éditeur visuel MCD / classes | D14: opus | E14: P10-T01 | F14: NON_FAIT | G14: canevas de diagramme (bibliothèque JS libre via JS Interop, choix en hypothèse) synchronisé avec le modèle sémantique : création d'entités, attributs, associations et cardinalités, héritage ; positions stockées dans element_diagramme ; une même entité apparaît dans les vues MCD et classes. | H14: test bUnit de l'enveloppe et test d'intégration : créer une association dans l'éditeur crée les 2 pattes en base ; déplacer un élément ne modifie que sa position. | J14: H-009 (OUVERTE)
A15: 8 | B15: P10-T08 | C15: Diagrammes documentaires | D15: sonnet | E15: P10-T01 | F15: NON_FAIT | G15: séquence, cas d'utilisation, activité, états, composants, déploiement, C4 en texte (Mermaid / PlantUML) avec aperçu ; BPMN via éditeur dédié (licence à vérifier, hypothèse) ; liens vers exigences et tickets. | H15: tests bUnit : l'aperçu se met à jour au changement de texte ; un diagramme invalide affiche l'erreur de syntaxe sans casser la page. | J15: H-010 (OUVERTE)
A16: 9 | B16: P10-T09 | C16: Versions, comparaison, validation et exports | D16: sonnet | E16: P10-T07, P10-T08 | F16: NON_FAIT | G16: versionner modèles et diagrammes, comparer deux versions (ajouts / suppressions / modifications), circuit de validation (architecte, chef de projet), exports PNG / SVG / PDF. | H16: tests : la comparaison de deux versions liste exactement les changements ; un modèle FIGE refuse toute modification.

Sheet P11
A1: P11 · Générateur de code
A2: Objectif : produire depuis le modèle un projet .NET/Blazor complet qui compile, conforme à l'architecture GP. Livrable : générateur Scriban + régénération incrémentale + dogfooding.
A3: Statut phase | B3: NON_DEMARREE
A4: Modèle conseillé | B4: opus
A5: Avancement | B5: =IF(COUNTA(B8:B200)=0,0,(COUNTIF(F8:F200,"A_VALIDER")+COUNTIF(F8:F200,"VALIDE"))/COUNTA(B8:B200))
A6: ← Retour à l'ordre d'exécution
A7: Ordre | B7: Code | C7: Tâche | D7: Modèle | E7: Dépend de | F7: Statut | G7: Explication | H7: Test de validation | I7: Retours utilisateur | J7: Hypothèses liées
A8: 1 | B8: P11-T01 | C8: Moteur de génération Scriban | D8: opus | E8: — | F8: NON_FAIT | G8: modèle de rendu (modules, entités, attributs typés C# / SQL, navigations, DTO, options), fonctions d'aide (PascalCase, camelCase, snake_case, pluriel français), portées ENTITE / MODULE / MODELE, résolution de chemin_sortie, templates par défaut embarqués et surchargeables en base. | H8: tests unitaires : rendu d'un template de test sur un modèle à 2 entités → sortie attendue exacte ; pluriels (« projet » → « projets », « travail » → « travaux » par table d'exceptions).
A9: 2 | B9: P11-T02 | C9: Templates backend | D9: opus | E9: P11-T01 | F9: NON_FAIT | G9: templates Entité, configuration EF, DTO (lecture, création, modification, liste), validateurs, mapper Mapperly, repository, service, orchestrateur, contrôleur — en *.g.cs et classes partial, respectant les couches GP. | H9: génération pour un modèle d'exemple (3 entités, 1 N:N, 1 énumération) puis dotnet build du résultat → 0 erreur, 0 avertissement ; les tests d'architecture GP appliqués au projet généré passent.
A10: 3 | B10: P11-T03 | C10: Templates socle : solution, base, Docker, CI | D10: opus | E10: P11-T02 | F10: NON_FAIT | G10: même structure que GestionProjet — deux projets <Nom>-Backend (couches en dossiers) et <Nom>-Front (+ tests et tests d'architecture) : .slnx, .csproj, Directory.Build.props, Program.cs, DbContext, migration initiale ou script SQL, Dockerfiles, docker-compose, .gitlab-ci.yml, README. | H10: le projet généré compile, sa migration s'applique sur pg-test, et son API répond 200 sur /health et sur un GET de liste.
A11: 4 | B11: P11-T04 | C11: Templates frontend | D11: sonnet | E11: P11-T03 | F11: NON_FAIT | G11: clients Api, services front, modèles de formulaire, pages Liste / Détail / Formulaire au balisage de la charte HCP — .explorer-table, .form-group, .toolbar-btn — embarquée dans le socle généré (contrôles selon controle_ui, listes déroulantes pour les associations, validation partagée). | H11: le front généré compile ; test bUnit généré pour une page Liste passe.
A12: 5 | B12: P11-T05 | C12: Régénération incrémentale et prévisualisation | D12: opus | E12: P11-T04 | F12: NON_FAIT | G12: régénérer sans toucher au code manuel (fichiers non .g.cs), détecter les conflits (fichier généré modifié à la main), prévisualiser le diff fichier par fichier avant écriture, rapport d'exécution. | H12: tests : ajout d'un attribut → seuls les .g.cs concernés changent ; un .g.cs modifié à la main est signalé et non écrasé sans confirmation.
A13: 6 | B13: P11-T06 | C13: Interface de génération et sortie ZIP | D13: sonnet | E13: P11-T05 | F13: NON_FAIT | G13: pages configuration (stack, architecture, dépôt cible), lancement, prévisualisation, téléchargement ZIP, historique des exécutions ; personnalisation des templates par l'équipe. | H13: tests : le ZIP contient l'arborescence attendue ; l'historique enregistre version du modèle, nombre de fichiers et statut.
A14: 7 | B14: P11-T07 | C14: Dogfooding : générer le squelette de GestionProjet | D14: opus | E14: P11-T06 | F14: NON_FAIT | G14: générer depuis le modèle de la plateforme (P10-T06) et comparer avec le code réel : structure à deux projets, entités, configurations EF, DTO. Rapport d'écarts et corrections des templates. | H14: le squelette généré compile ; docs/modules/generation.md contient le rapport d'écarts avec, pour chaque écart, la décision (corrigé / assumé).

Sheet P12
A1: P12 · Intégration GitLab
A2: Objectif : relier projets, tickets et code GitLab. Livrable : traçabilité commit / MR / pipeline ↔ ticket. ⚠️ Instance GitLab requise (H-002).
A3: Statut phase | B3: NON_DEMARREE
A4: Modèle conseillé | B4: sonnet
A5: Avancement | B5: =IF(COUNTA(B8:B200)=0,0,(COUNTIF(F8:F200,"A_VALIDER")+COUNTIF(F8:F200,"VALIDE"))/COUNTA(B8:B200))
A6: ← Retour à l'ordre d'exécution
A7: Ordre | B7: Code | C7: Tâche | D7: Modèle | E7: Dépend de | F7: Statut | G7: Explication | H7: Test de validation | I7: Retours utilisateur | J7: Hypothèses liées
A8: 1 | B8: P12-T01 | C8: Client GitLab | D8: sonnet | E8: — | F8: NON_FAIT | G8: client API v4 dans Infrastructure/ (jeton depuis la configuration sécurisée, pagination, gestion des limites de débit, erreurs) ; tests avec un serveur HTTP simulé. | H8: tests unitaires (WireMock.Net) : pagination sur 3 pages, 429 → nouvelle tentative, 401 → erreur explicite. | J8: H-011 (OUVERTE)
A9: 2 | B9: P12-T02 | C9: Création et liaison des dépôts | D9: sonnet | E9: P12-T01 | F9: NON_FAIT | G9: à la création d'un projet (option), création du groupe et des dépôts (backend, frontend, infra), branches protégées, modèles de MR ; liaison projet ↔ dépôts (nouvelle table + migration + MLD). | H9: tests avec serveur simulé : séquence d'appels attendue ; comparer-schema.py à 0 écart après mise à jour du schéma de référence.
A10: 3 | B10: P12-T03 | C10: Envoi du code généré vers GitLab | D10: sonnet | E10: P12-T02 | F10: NON_FAIT | G10: pousser une génération sur une branche dédiée via l'API commits (actions create / update), puis ouvrir une MR. | H10: test avec serveur simulé : un seul commit contenant tous les fichiers, branche et MR créées.
A11: 4 | B11: P12-T04 | C11: Webhooks entrants | D11: sonnet | E11: P12-T01 | F11: NON_FAIT | G11: réception push / MR / pipeline (jeton secret vérifié), rattachement par numéro de ticket dans branche, commit ou titre de MR ; transitions automatiques (MR ouverte → En revue, MR fusionnée → À tester) ; imputation « Time 2h ». | H11: tests : charge utile réelle d'exemple → lien créé et statut changé ; jeton invalide → 401 ; « Time 2h » → saisie de 2 h source GITLAB.
A12: 5 | B12: P12-T05 | C12: Vues GitLab dans les tickets | D12: sonnet | E12: P12-T04 | F12: NON_FAIT | G12: onglet « Code » d'un ticket (branches, commits, MR, état du pipeline), bouton « Créer la branche » nommée feature/<numéro>-<slug>. | H12: tests bUnit : affichage des états de pipeline ; nom de branche généré conforme.
A13: 6 | B13: P12-T06 | C13: Releases et notes de version | D13: sonnet | E13: P12-T04 | F13: NON_FAIT | G13: tags et releases liés aux phases, notes de version générées depuis les tickets fusionnés, correspondance milestones ↔ phases. | H13: test : les notes de version listent exactement les tickets fusionnés entre deux tags.

Sheet P13
A1: P13 · Déploiement Docker
A2: Objectif : environnements, déploiements via pipeline, validation avant production, DORA. Livrable : module Déploiement.
A3: Statut phase | B3: NON_DEMARREE
A4: Modèle conseillé | B4: sonnet
A5: Avancement | B5: =IF(COUNTA(B8:B200)=0,0,(COUNTIF(F8:F200,"A_VALIDER")+COUNTIF(F8:F200,"VALIDE"))/COUNTA(B8:B200))
A6: ← Retour à l'ordre d'exécution
A7: Ordre | B7: Code | C7: Tâche | D7: Modèle | E7: Dépend de | F7: Statut | G7: Explication | H7: Test de validation | I7: Retours utilisateur | J7: Hypothèses liées
A8: 1 | B8: P13-T01 | C8: Environnements : modèle et API | D8: sonnet | E8: — | F8: NON_FAIT | G8: tables environnement et deploiement (modélisées dans le module Modélisation, migration, MLD mis à jour) ; CRUD environnements (dev, recette, préprod, prod : URL, serveurs, responsable). | H8: comparer-schema.py à 0 écart ; tests CRUD.
A9: 2 | B9: P13-T02 | C9: Déclenchement des déploiements | D9: sonnet | E9: P13-T01 | F9: NON_FAIT | G9: déclencher le job manuel du pipeline GitLab pour une version et un environnement, suivre son état, historique (qui, quand, version, tickets inclus). | H9: test avec serveur GitLab simulé : déclenchement → déploiement EN_COURS puis SUCCES sur webhook pipeline.
A10: 3 | B10: P13-T03 | C10: État des environnements | D10: sonnet | E10: P13-T01 | F10: NON_FAIT | G10: sonde de santé périodique des URL d'environnement, version déployée, lien vers les journaux. | H10: test avec un serveur local : /health 200 → OK ; arrêt → KO après le délai.
A11: 4 | B11: P13-T04 | C11: Validation avant production et rollback | D11: sonnet | E11: P13-T02 | F11: NON_FAIT | G11: déploiement en production soumis à approbation hiérarchique ; rollback = redéploiement du tag précédent. | H11: tests : déploiement prod sans approbation → refusé ; rollback cible le tag précédent réussi.
A12: 5 | B12: P13-T05 | C12: Indicateurs DORA et pages | D12: sonnet | E12: P13-T04 | F12: NON_FAIT | G12: fréquence de déploiement, délai de livraison, taux d'échec, temps de rétablissement ; pages environnements et historique. | H12: tests chiffrés sur un historique simulé ; tests bUnit des pages.

Sheet P14
A1: P14 · Cadrage, exigences et conception des écrans
A2: Objectif : modules Brainstorming, Analyse / exigences, Conception des écrans, traçabilité. Livrable : de l'idée à l'écran spécifié.
A3: Statut phase | B3: NON_DEMARREE
A4: Modèle conseillé | B4: sonnet
A5: Avancement | B5: =IF(COUNTA(B8:B200)=0,0,(COUNTIF(F8:F200,"A_VALIDER")+COUNTIF(F8:F200,"VALIDE"))/COUNTA(B8:B200))
A6: ← Retour à l'ordre d'exécution
A7: Ordre | B7: Code | C7: Tâche | D7: Modèle | E7: Dépend de | F7: Statut | G7: Explication | H7: Test de validation | I7: Retours utilisateur | J7: Hypothèses liées
A8: 1 | B8: P14-T01 | C8: Modèle de données cadrage / exigences / écrans | D8: opus | E8: — | F8: NON_FAIT | G8: modéliser (dans le module Modélisation) puis migrer : idée, session d'atelier, post-it, vote, exigence, user story, critère d'acceptation, règle de gestion, glossaire, demande de changement, écran, champ d'écran, action d'écran, liens de traçabilité ; mettre à jour MLD et schéma de référence. | H8: comparer-schema.py à 0 écart ; contrôle de cohérence du modèle (P10-T02) à 0 défaut.
A9: 2 | B9: P14-T02 | C9: Brainstorming et tableau blanc | D9: sonnet | E9: P14-T01 | F9: NON_FAIT | G9: fiches idées, tableau blanc collaboratif temps réel (SignalR) : post-its, regroupements, votes, minuteur, mode anonyme ; conversion post-it → exigence / tâche. | H9: test d'intégration SignalR à 2 clients : un post-it ajouté par l'un apparaît chez l'autre ; la conversion crée l'exigence liée.
A10: 3 | B10: P14-T03 | C10: Modèles d'ateliers et priorisation | D10: sonnet | E10: P14-T02 | F10: NON_FAIT | G10: SWOT, 5 Why, Persona, Lean Canvas, MoSCoW, cartographie des parties prenantes ; scoring RICE, valeur / effort ; note de cadrage générée. | H10: tests : score RICE calculé exact ; la note de cadrage contient les sections du modèle.
A11: 4 | B11: P14-T04 | C11: Exigences, user stories et changements | D11: sonnet | E11: P14-T01 | F11: NON_FAIT | G11: exigences fonctionnelles / non fonctionnelles numérotées, user stories, critères Gherkin, règles de gestion RG-xxx, glossaire, demandes de changement avec analyse d'impact en jours-homme et validation. | H11: tests : numérotation continue par projet ; une demande de changement validée crée une nouvelle version de l'exigence sans perdre l'ancienne.
A12: 5 | B12: P14-T05 | C12: Conception des écrans | D12: sonnet | E12: P14-T04 | F12: NON_FAIT | G12: inventaire des écrans, fiche écran (composants, champs liés aux attributs du modèle, actions, règles), arborescence et parcours, wireframes simples en glisser-déposer ; ces fiches alimentent les templates de pages du générateur. | H12: tests : un champ lié à un attribut obligatoire hérite de la contrainte ; génération de page (P11) utilisant la fiche écran → ordre des champs respecté.
A13: 6 | B13: P14-T06 | C13: Matrice de traçabilité | D13: opus | E13: P14-T05 | F13: NON_FAIT | G13: matrice exigence ↔ cas d'utilisation ↔ écran ↔ entité ↔ ticket ↔ test ↔ MR, détection des trous (exigence sans test, écran sans exigence…), export. | H13: jeu de données avec 3 trous connus → la matrice signale exactement ces 3 trous.

Sheet P15
A1: P15 · Qualité, recette et DevSecOps
A2: Objectif : recette outillée et sécurité intégrée au cycle. Livrable : modules Qualité et Sécurité.
A3: Statut phase | B3: NON_DEMARREE
A4: Modèle conseillé | B4: sonnet
A5: Avancement | B5: =IF(COUNTA(B8:B200)=0,0,(COUNTIF(F8:F200,"A_VALIDER")+COUNTIF(F8:F200,"VALIDE"))/COUNTA(B8:B200))
A6: ← Retour à l'ordre d'exécution
A7: Ordre | B7: Code | C7: Tâche | D7: Modèle | E7: Dépend de | F7: Statut | G7: Explication | H7: Test de validation | I7: Retours utilisateur | J7: Hypothèses liées
A8: 1 | B8: P15-T01 | C8: Modèle de données qualité et sécurité | D8: opus | E8: — | F8: NON_FAIT | G8: plan de test, cas de test, campagne, exécution, détail de vulnérabilité (CVSS, CWE, CVE, actif, SLA), checklist de sécurité, menace STRIDE ; migration, MLD. | H8: comparer-schema.py à 0 écart ; contrôle de cohérence à 0 défaut.
A9: 2 | B9: P15-T02 | C9: Plans, cas, campagnes et exécutions | D9: sonnet | E9: P15-T01 | F9: NON_FAIT | G9: cahier de recette généré depuis les critères d'acceptation, campagnes par version et environnement, exécution pas à pas, création d'une anomalie depuis un test en échec (liée à l'exigence). | H9: tests : une exécution en échec crée un ticket ANOMALIE_RECETTE lié ; couverture des exigences calculée exacte.
A10: 3 | B10: P15-T03 | C10: Résultats automatisés et qualité de code | D10: sonnet | E10: P15-T02 | F10: NON_FAIT | G10: import des rapports JUnit des pipelines GitLab ; intégration SonarQube (si disponible, hypothèse) : dette, couverture, problèmes. | H10: test : un rapport JUnit d'exemple → exécutions créées avec les bons statuts. | J10: H-012 (OUVERTE)
A11: 4 | B11: P15-T04 | C11: Gestion des vulnérabilités | D11: sonnet | E11: P15-T01 | F11: NON_FAIT | G11: calcul CVSS 3.1, SLA de correction selon la criticité, import des rapports GitLab SAST / DAST / dépendances / conteneurs → tickets VULNERABILITE (dédoublonnés). | H11: tests : vecteur CVSS de référence → score exact ; import du même rapport deux fois → aucun doublon.
A12: 5 | B12: P15-T05 | C12: Checklists de sécurité et menaces | D12: sonnet | E12: P15-T01 | F12: NON_FAIT | G12: checklists OWASP Top 10 / ASVS par phase, modélisation STRIDE liée aux diagrammes d'architecture, analyse de risques simplifiée. | H12: tests : une checklist incomplète empêche la validation de la phase si le paramètre l'exige.
A13: 6 | B13: P15-T06 | C13: PV de recette | D13: sonnet | E13: P15-T02 | F13: NON_FAIT | G13: génération du PV (VABF / VSR) depuis une campagne, signature / validation métier tracée. | H13: test : le PV liste les cas passés / échoués et les réserves ; la validation est enregistrée dans l'historique.

Sheet P16
A1: P16 · Documentation, méthodes agiles, automatisation et API
A2: Objectif : wiki et livrables générés, Scrum, automatisations, API publique, imports. Livrable : modules 11, 21, 23, 24.
A3: Statut phase | B3: NON_DEMARREE
A4: Modèle conseillé | B4: sonnet
A5: Avancement | B5: =IF(COUNTA(B8:B200)=0,0,(COUNTIF(F8:F200,"A_VALIDER")+COUNTIF(F8:F200,"VALIDE"))/COUNTA(B8:B200))
A6: ← Retour à l'ordre d'exécution
A7: Ordre | B7: Code | C7: Tâche | D7: Modèle | E7: Dépend de | F7: Statut | G7: Explication | H7: Test de validation | I7: Retours utilisateur | J7: Hypothèses liées
A8: 1 | B8: P16-T01 | C8: Wiki de projet | D8: sonnet | E8: — | F8: NON_FAIT | G8: pages Markdown par projet (arborescence, versions, comparaison, liens vers éléments), modèles de pages ; migration + MLD. | H8: tests : restaurer une version antérieure ; un lien vers un ticket hors périmètre n'en révèle pas le titre.
A9: 2 | B9: P16-T02 | C9: Génération des livrables documentaires | D9: opus | E9: P16-T01 | F9: NON_FAIT | G9: SFG / SFD, dossier de conception (diagrammes inclus), DAT, dictionnaire de données, cahier de recette, en Word et PDF au format officiel, depuis les données saisies. | H9: tests : le dictionnaire de données contient toutes les entités du modèle ; le document Word s'ouvre (validation OpenXML) et contient les titres attendus.
A10: 3 | B10: P16-T03 | C10: Mode Scrum | D10: sonnet | E10: — | F10: NON_FAIT | G10: sprints dans une phase (mode hybride), planification selon la capacité, planning poker, rétrospectives (actions → tickets), burndown, burnup, vélocité, CFD. | H10: tests chiffrés : burndown d'un sprint simulé ; capacité du sprint = somme des disponibilités.
A11: 4 | B11: P16-T04 | C11: Moteur d'automatisation | D11: opus | E11: — | F11: NON_FAIT | G11: règles « Quand (événement) / Si (conditions) / Alors (actions) » : assignation, notification, changement de statut, escalade ; protection contre les boucles ; journal d'exécution. | H11: tests : règle « ticket bloqué > 3 jours → notifier le chef » déclenchée au bon moment ; deux règles qui se déclenchent mutuellement → arrêt après la limite et alerte.
A12: 5 | B12: P16-T05 | C12: API publique et webhooks sortants | D12: sonnet | E12: — | F12: NON_FAIT | G12: API versionnée (/api/v1), jetons d'accès personnels (portée, expiration, révocation), limitation de débit, webhooks sortants signés (HMAC). | H12: tests : jeton révoqué → 401 ; dépassement du débit → 429 ; signature HMAC vérifiable par le destinataire.
A13: 6 | B13: P16-T06 | C13: Imports Jira, Redmine, Trello, CSV, Excel | D13: sonnet | E13: P16-T05 | F13: NON_FAIT | G13: assistants d'import avec correspondance des champs et des statuts, simulation avant import, rapport. | H13: tests : un export Jira d'exemple → tâches et tickets créés avec les bons statuts ; la simulation n'écrit rien.

Sheet P17
A1: P17 · Expérience utilisateur transverse et accessibilité
A2: Objectif : recherche, productivité, PWA, accessibilité RGAA, tests E2E. Livrable : application fluide et accessible.
A3: Statut phase | B3: NON_DEMARREE
A4: Modèle conseillé | B4: sonnet
A5: Avancement | B5: =IF(COUNTA(B8:B200)=0,0,(COUNTIF(F8:F200,"A_VALIDER")+COUNTIF(F8:F200,"VALIDE"))/COUNTA(B8:B200))
A6: ← Retour à l'ordre d'exécution
A7: Ordre | B7: Code | C7: Tâche | D7: Modèle | E7: Dépend de | F7: Statut | G7: Explication | H7: Test de validation | I7: Retours utilisateur | J7: Hypothèses liées
A8: 1 | B8: P17-T01 | C8: Recherche globale et palette de commandes | D8: sonnet | E8: — | F8: NON_FAIT | G8: recherche plein texte PostgreSQL (configuration française, tsvector + index GIN) filtrée par périmètre ; palette Ctrl+K (navigation, actions) ; raccourcis clavier documentés. | H8: tests : la recherche « affectation » trouve « affecter » (racinisation) ; aucun résultat hors périmètre ; test bUnit de la palette au clavier.
A9: 2 | B9: P17-T02 | C9: Vues enregistrées et filtres avancés | D9: sonnet | E9: — | F9: NON_FAIT | G9: filtres combinables, vues personnelles et partagées, langage de requête simple (statut = EN_COURS ET priorite >= HAUTE) avec analyseur et messages d'erreur. | H9: tests de l'analyseur (requêtes valides et invalides) ; une vue partagée respecte le périmètre de chaque lecteur.
A10: 3 | B10: P17-T03 | C10: Favoris, récents, « Ma journée » | D10: haiku | E10: — | F10: NON_FAIT | G10: favoris, éléments récents, page « Ma journée » (tickets du jour, réunions, temps à saisir). | H10: tests bUnit : un favori ajouté apparaît dans le menu ; « Ma journée » liste les échéances du jour.
A11: 4 | B11: P17-T04 | C11: PWA | D11: sonnet | E11: — | F11: NON_FAIT | G11: manifeste, service worker (cache des ressources statiques, lecture hors ligne des derniers éléments consultés), invitation d'installation. | H11: le manifeste est valide (champs requis) ; test E2E : page consultée accessible hors ligne en lecture.
A12: 5 | B12: P17-T05 | C12: Audit et corrections d'accessibilité | D12: sonnet | E12: — | F12: NON_FAIT | G12: audit automatisé axe-core via Playwright .NET sur les pages principales, corrections, déclaration d'accessibilité (RGAA / WCAG 2.2 AA). | H12: test E2E : 0 violation axe « serious » ou « critical » sur les 15 pages principales.
A13: 6 | B13: P17-T06 | C13: Arabe RTL et revue i18n | D13: sonnet | E13: — | F13: NON_FAIT | G13: revue complète des traductions, mise en miroir correcte des composants (Gantt, Kanban, fil d'Ariane), formats de date. | H13: test qui échoue si une clé de ressource existe en fr mais pas en en / ar ; capture E2E en arabe sans débordement.
A14: 7 | B14: P17-T07 | C14: Accueil guidé et aide contextuelle | D14: haiku | E14: — | F14: NON_FAIT | G14: parcours d'accueil par rôle, info-bulles d'aide, liens vers le manuel. | H14: tests bUnit : le parcours diffère selon le rôle ; il ne s'affiche qu'une fois.
A15: 8 | B15: P17-T08 | C15: Tests E2E des parcours critiques | D15: sonnet | E15: P17-T05 | F15: NON_FAIT | G15: Playwright .NET : création projet → affectation en cascade → équipe → phases / tâches / tickets → saisie et validation des temps → tableau de bord directeur. | H15: dotnet test tests/Gprojet-E2E vert sur l'environnement docker compose.

Sheet P18
A1: P18 · Sécurité Keycloak et durcissement
A2: Objectif : authentification réelle (Keycloak, LDAP / AD) et durcissement ASVS. Livrable : application prête pour l'homologation.
A3: Statut phase | B3: NON_DEMARREE
A4: Modèle conseillé | B4: opus
A5: Avancement | B5: =IF(COUNTA(B8:B200)=0,0,(COUNTIF(F8:F200,"A_VALIDER")+COUNTIF(F8:F200,"VALIDE"))/COUNTA(B8:B200))
A6: ← Retour à l'ordre d'exécution
A7: Ordre | B7: Code | C7: Tâche | D7: Modèle | E7: Dépend de | F7: Statut | G7: Explication | H7: Test de validation | I7: Retours utilisateur | J7: Hypothèses liées
A8: 1 | B8: P18-T01 | C8: Realm Keycloak | D8: opus | E8: — | F8: NON_FAIT | G8: export JSON versionné du realm (client confidentiel du backend pour le BFF, client de l'API publique, rôles, mappers, politique de sessions), service Keycloak dans docker compose, fédération LDAP / AD paramétrée (hypothèse sur l'annuaire). | H8: docker compose --profile keycloak up importe le realm ; obtention d'un jeton de test pour un utilisateur de démo. | J8: H-013 (OUVERTE, bloquante)
A9: 2 | B9: P18-T02 | C9: BFF OIDC et API JWT | D9: opus | E9: P18-T01 | F9: NON_FAIT | G9: BFF : code + PKCE, cookie sécurisé, rafraîchissement, déconnexion globale ; API : validation JWT (audience, émetteur, durée) ; correspondance keycloak_sub ↔ agent (premier login par matricule). | H9: tests d'intégration avec Keycloak de test : connexion complète, jeton expiré → rafraîchi, déconnexion → cookie invalidé ; jeton d'une autre audience → 401.
A10: 3 | B10: P18-T03 | C10: MFA et politiques de session | D10: sonnet | E10: P18-T01 | F10: NON_FAIT | G10: MFA (TOTP) obligatoire pour les rôles de chef et d'administrateur, politique de mots de passe, durée de session, verrouillage. | H10: test : un chef sans MFA configuré est redirigé vers l'enrôlement.
A11: 4 | B11: P18-T04 | C11: Revue de sécurité ASVS niveau 2 | D11: opus | E11: P18-T02 | F11: NON_FAIT | G11: en-têtes (CSP stricte, HSTS, X-Content-Type-Options, Referrer-Policy), anti-CSRF, limitation de débit, validation des téléversements, injection SQL / XSS, journalisation de sécurité ; corrections ; rapport docs/SECURITE.md. | H11: tests automatisés des en-têtes et du CSRF ; scan DAST de base (ZAP baseline via conteneur) sans alerte haute ; rapport complété.
A12: 5 | B12: P18-T05 | C12: Sauvegardes et restauration | D12: sonnet | E12: — | F12: NON_FAIT | G12: sauvegarde planifiée (pg_dump chiffré, rétention), procédure de restauration documentée et testée. | H12: script de test : sauvegarde → base détruite → restauration → comptages identiques.
A13: 6 | B13: P18-T06 | C13: Confidentialité et données personnelles | D13: sonnet | E13: — | F13: NON_FAIT | G13: restrictions par classification (DIFFUSION_RESTREINTE : membres nommés uniquement), export des données d'un agent, anonymisation d'un agent parti, durées de conservation. | H13: tests : un directeur ne voit pas le détail d'un projet DIFFUSION_RESTREINTE dont il n'est pas membre (seulement sa ligne agrégée) ; l'anonymisation conserve les temps mais retire l'identité.
A14: 7 | B14: P18-T07 | C14: Retrait de l'authentification de développement en production | D14: haiku | E14: P18-T02 | F14: NON_FAIT | G14: garantir que DevAuthHandler et la page de connexion de développement n'existent qu'en Development / Test. | H14: test d'intégration en environnement Production : l'en-tête X-Dev-Matricule est ignoré (401) et /bff/login redirige vers Keycloak.

Sheet P19
A1: P19 · Performance, recette finale et mise en production
A2: Objectif : tenue en charge, observabilité, documentation d'exploitation, recette et go-live. Livrable : version 1.0 en production.
A3: Statut phase | B3: NON_DEMARREE
A4: Modèle conseillé | B4: sonnet
A5: Avancement | B5: =IF(COUNTA(B8:B200)=0,0,(COUNTIF(F8:F200,"A_VALIDER")+COUNTIF(F8:F200,"VALIDE"))/COUNTA(B8:B200))
A6: ← Retour à l'ordre d'exécution
A7: Ordre | B7: Code | C7: Tâche | D7: Modèle | E7: Dépend de | F7: Statut | G7: Explication | H7: Test de validation | I7: Retours utilisateur | J7: Hypothèses liées
A8: 1 | B8: P19-T01 | C8: Jeu de données volumineux et tests de charge | D8: sonnet | E8: — | F8: NON_FAIT | G8: générateur de données (200 projets, 5 000 tâches, 100 000 tickets, 2 ans de temps), scénarios de charge (NBomber) sur tableaux de bord, listes et saisie des temps. | H8: rapport NBomber : p95 < 2 s sur les tableaux de bord et < 500 ms sur les listes paginées avec 50 utilisateurs simultanés.
A9: 2 | B9: P19-T02 | C9: Optimisations | D9: sonnet | E9: P19-T01 | F9: NON_FAIT | G9: analyse des plans d'exécution (EXPLAIN ANALYZE), index manquants, requêtes N+1, cache de lecture ; mise à jour du schéma de référence si index ajoutés. | H9: nouveau passage NBomber conforme aux seuils ; comparer-schema.py à 0 écart.
A10: 3 | B10: P19-T03 | C10: Observabilité | D10: sonnet | E10: — | F10: NON_FAIT | G10: OpenTelemetry (traces, métriques, journaux), profil docker compose d'observabilité, tableaux de bord et alertes (erreurs 5xx, latence, file de jobs). | H10: une requête produit une trace corrélée navigateur → backend → base visible dans l'outil ; une alerte se déclenche sur erreurs simulées.
A11: 4 | B11: P19-T04 | C11: Documentation d'exploitation et manuels | D11: haiku | E11: — | F11: NON_FAIT | G11: docs/EXPLOITATION.md (installation, configuration, sauvegarde, mise à jour, supervision) et manuels utilisateur par rôle (directeur, chef de division, chef de service, agent, administrateur). | H11: chaque manuel couvre les écrans de son rôle (liste de contrôle comparée au menu par rôle) ; chaque commande citée existe.
A12: 5 | B12: P19-T05 | C12: Recette finale | D12: sonnet | E12: P19-T02, P19-T03 | F12: NON_FAIT | G12: campagne de recette complète dans le module Qualité sur l'environnement de recette, correction des anomalies bloquantes, PV de recette. | H12: PV généré : 0 anomalie bloquante ou majeure ouverte ; tests E2E verts.
A13: 6 | B13: P19-T06 | C13: Mise en production | D13: sonnet | E13: P19-T05 | F13: NON_FAIT | G13: tag de version 1.0, images publiées, déploiement de production via le module Déploiement avec approbation, liste de contrôle de mise en production, plan de retour arrière. | H13: liste de contrôle cochée dans docs/MISE-EN-PRODUCTION.md ; /health/ready de production à 200 ; procédure de rollback répétée en préproduction.

Sheet Hypothèses
A1: Feuille des hypothèses
A2: Réponse : /repondre-hypothese H-00x <réponse>. Une hypothèse bloquante ouverte met sa tâche en BLOQUE.
A4: Code | B4: Tâche | C4: Statut | D4: Bloquante | E4: Date | F4: Question | G4: Hypothèse par défaut | H4: Impact si fausse | I4: Réponse utilisateur
A5: H-001 | B5: P3-T01 | C5: REPONDUE | D5: oui | E5: 2026-10-16 10:54 | F5: Docker n'est pas installé sur le poste. Faut-il installer Docker Desktop (ou Rancher Desktop / Podman) avant la phase P3 ? | G5: Docker Desktop sera installé par l'utilisateur avant P3 ; P3-T03, P3-T04 et P3-T05 peuvent avancer sans Docker. | H5: Sans moteur de conteneurs, les images, docker compose et les tests Testcontainers ne peuvent pas être validés. | I5: 23) : Docker 29 est installé
A6: H-002 | B6: P3-T04 | C6: REPONDUE | D6: non | E6: 2026-10-16 10:54 | F6: Quelle instance GitLab (URL, version, runners Docker disponibles) exécutera le pipeline ? | G6: GitLab self-managed ≥ 17 avec runners Docker et Container Registry activé ; validation du YAML par script local, CI Lint GitLab dès que l'URL est connue. | H6: Mots-clés ou templates de sécurité indisponibles selon l'édition (SAST/DAST complets = Ultimate). | I6: 48) : Choix utilisateur (2026-10-16) : le dépôt du projet est sur GitHub (hajar-hamid-coder/gprojet, public) ; l'intégration continue se fait avec GitHub Actions et l'image est publiée sur ghcr.io. GitLab reste une intégration fonctionnelle de la plateforme (P12-P13).
A7: H-003 | B7: P0-T06 | C7: REPONDUE | D7: non | E7: 2026-10-16 10:54 | F7: Node.js n'est pas installé : faut-il l'installer pour Ponytail (hooks d'activation) et l'installation du skill motion-design ? | G7: Installer Node.js LTS via scripts/installer-outils.ps1 ; sans Node, les skills Ponytail restent utilisables manuellement et motion-design est copié par git clone. | H7: Ponytail ne s'active pas automatiquement à chaque session. | I7: 23) : Node.js v26 est installé
A8: H-004 | B8: P1-T09 | C8: REPONDUE | D8: non | E8: 2026-10-16 10:54 | F8: Pour exécuter l'API en développement (hors tests), quelle base PostgreSQL utiliser et avec quel compte ? | G8: Tests sur l'instance jetable pg-test ; exécution locale sur le service PostgreSQL 18 du poste avec une chaîne de connexion définie par l'utilisateur dans dotnet user-secrets (Claude ne connaît aucun mot de passe). | H8: Si une autre base est imposée, seule la configuration change. | I8: 31) : Base de développement fournie : gprojet (vide) sur localhost:5432, compte postgres. Chaîne de connexion dans .claude/settings.local.json (variable ConnectionStrings__Gp, non versionnée). Les tests restent sur l'instance jetable pg-test, jamais sur gprojet.
A9: H-005 | B9: P6-T11 | C9: OUVERTE | D9: non | E9: 2026-10-16 10:54 | F9: Quelle bibliothèque de Gantt utiliser (licence compatible marché public) ? | G9: Frappe Gantt (MIT) via JS Interop ; vue PERT avec Cytoscape.js (MIT). | H9: Fonctions avancées (ressources, baseline visuelle) à développer soi-même ; alternative commerciale DHTMLX / Syncfusion. | I9: en attente
A10: H-006 | B10: P8-T07 | C10: OUVERTE | D10: non | E10: 2026-10-16 10:54 | F10: Bibliothèques d'export Excel et PDF autorisées ? | G10: ClosedXML (MIT) pour Excel, PDFsharp / MigraDoc (MIT) pour PDF ; QuestPDF écarté (licence communautaire conditionnelle). | H10: Mise en page PDF plus verbeuse à coder. | I10: en attente
A11: H-007 | B11: P8-T07 | C11: OUVERTE | D11: non | E11: 2026-10-16 10:54 | F11: Charte officielle (logo, en-tête, mentions) à appliquer sur les exports et les livrables ? | G11: Logo et en-tête génériques paramétrables par entité, remplacés par les fichiers officiels fournis plus tard. | H11: Exports à régénérer une fois la charte fournie. | I11: en attente
A12: H-008 | B12: P9-T02 | C12: OUVERTE | D12: non | E12: 2026-10-16 10:54 | F12: Les pièces jointes doivent-elles passer par un antivirus ? | G12: Point d'extension IAnalyseurFichier ; implémentation ClamAV (conteneur) optionnelle, désactivée en développement. | H12: Sans antivirus, risque de dépôt de fichiers malveillants en production. | I12: en attente
A13: H-009 | B13: P10-T07 | C13: OUVERTE | D13: non | E13: 2026-10-16 10:54 | F13: Quelle bibliothèque pour l'éditeur visuel MCD / classes ? | G13: JointJS core (MPL-2.0) via JS Interop. | H13: Si refusée, alternative Drawflow (MIT) avec plus de développement. | I13: en attente
A14: H-010 | B14: P10-T08 | C14: OUVERTE | D14: non | E14: 2026-10-16 10:54 | F14: bpmn-js impose de conserver le filigrane bpmn.io : est-ce acceptable ? | G14: Oui, filigrane conservé conformément à la licence. | H14: Sinon, BPMN limité à un rendu texte / Mermaid. | I14: en attente
A15: H-011 | B15: P12-T01 | C15: OUVERTE | D15: non | E15: 2026-10-16 10:54 | F15: URL GitLab et jeton technique (portée api) pour l'intégration réelle ? | G15: Développement et tests sur serveur GitLab simulé ; l'URL et le jeton seront fournis via la configuration sécurisée avant la recette. | H15: Intégration non testée de bout en bout tant que l'instance n'est pas fournie. | I15: en attente
... A27: H-023 | B27: P1-T06 | C27: OUVERTE | D27: non | E27: 2026-10-16 14:45 | F27: La comparaison de schéma doit-elle couvrir l'ordre des colonnes et le contenu des données de référence ? | G27: Non : type, nullabilité, défaut, contraintes, index, triggers, fonctions et nombre de lignes par table suffisent ; les données sont une copie figée de 02 embarquée dans la migration | H27: Une différence d'ordre de colonnes ou de valeurs (même nombre de lignes) ne serait pas détectée | I27: en attente

Sheet Légende
A1: Légende et règles
A3: Élément | B3: Valeur | C3: Signification
A4: Statut de tâche | B4: NON_FAIT | C4: Pas commencée.
A5: Statut de tâche | B5: EN_COURS | C5: En cours d'exécution par Claude (une seule à la fois).
A6: Statut de tâche | B6: A_VALIDER | C6: Terminée par Claude, test de validation réussi et rejoué par le vérificateur.
A7: Statut de tâche | B7: VALIDE | C7: Validée par l'utilisateur avec la phase (/valider-phase).
A8: Statut de tâche | B8: BLOQUE | C8: En attente de la réponse à une hypothèse bloquante (/repondre-hypothese).
A9: Statut de phase | B9: NON_DEMARREE | C9: Pas lancée. Se lance avec /lancer-phase quand la précédente est VALIDEE.
A10: Statut de phase | B10: EN_COURS | C10: Claude exécute les tâches de façon autonome.
A11: Statut de phase | B11: A_VALIDER | C11: Toutes les tâches sont A_VALIDER : Claude attend votre validation.
A12: Statut de phase | B12: VALIDEE | C12: Validée par l'utilisateur.
A13: Modèle | B13: opus | C13: Tâche complexe : architecture, sécurité, algorithmes, générateur.
A14: Modèle | B14: sonnet | C14: Tâche moyenne : CRUD, pages, services, intégrations.
... A17: Fichier | B17: BACKLOG.xlsx | C17: Vue générée depuis backlog/BACKLOG.md à chaque changement. Toute modification manuelle est écrasée.
